{
    "FAD": [
      {
        "PRESCRIPTION NAME": "Thiamine (Vit B1)",
        "Agreed price": 2.5
      },
      {
        "PRESCRIPTION NAME": "Calcium Gluconate Tabs 600mg (per tab)",
        "Agreed price": 3.75
      },
      {
        "PRESCRIPTION NAME": "Cyanocobalamin (B12) Tabs (per tab)",
        "Agreed price": 3.75
      },
      {
        "PRESCRIPTION NAME": "Yeast BPC Tabs 300mg (per tab)",
        "Agreed price": 3.75
      },
      {
        "PRESCRIPTION NAME": "BANOCIDE 50MG (per tab)",
        "Agreed price": 6.25
      },
      {
        "PRESCRIPTION NAME": "BISACODYL 5MG (per tab)",
        "Agreed price": 6.25
      },
      {
        "PRESCRIPTION NAME": "INDOMEHACINE (per tab)",
        "Agreed price": 6.25
      },
      {
        "PRESCRIPTION NAME": "PROMETHAZINE 25MG (per tab)",
        "Agreed price": 6.25
      },
      {
        "PRESCRIPTION NAME": "Riboflavine (Vit B2) Tabs 5mg (per tab)",
        "Agreed price": 6.25
      },
      {
        "PRESCRIPTION NAME": "VASOPRIN 75MG TAB",
        "Agreed price": 6.25
      },
      {
        "PRESCRIPTION NAME": "VIT C 100MG (per tab)",
        "Agreed price": 6.25
      },
      {
        "PRESCRIPTION NAME": "CHLORAMPHENICOL 250MG (PER TAB)",
        "Agreed price": 7.5
      },
      {
        "PRESCRIPTION NAME": "Stilboesterol Tabs (per tab)",
        "Agreed price": 7.5
      },
      {
        "PRESCRIPTION NAME": "ASPIRIN 75MG  (per tab)",
        "Agreed price": 10
      },
      {
        "PRESCRIPTION NAME": "CALCIUM LACTATE 300MG (per tab)",
        "Agreed price": 10
      },
      {
        "PRESCRIPTION NAME": "FERROUS SULHATE 20MG (per tab)",
        "Agreed price": 10
      },
      {
        "PRESCRIPTION NAME": "PARACETAMOL  (per tab)",
        "Agreed price": 10
      },
      {
        "PRESCRIPTION NAME": "SALBUTAMOL 4MG (per tab)",
        "Agreed price": 10
      },
      {
        "PRESCRIPTION NAME": "FALVITONE (PER CAP)",
        "Agreed price": 11.25
      },
      {
        "PRESCRIPTION NAME": "AMINOPHYLLINE TABS (per tab)",
        "Agreed price": 12
      },
      {
        "PRESCRIPTION NAME": "ARTANE 5MG (per tab)",
        "Agreed price": 12.5
      },
      {
        "PRESCRIPTION NAME": "AVOMINE 25MG (per tab)",
        "Agreed price": 12.5
      },
      {
        "PRESCRIPTION NAME": "HALOPERIDOL 5MG (per tab)",
        "Agreed price": 12.5
      },
      {
        "PRESCRIPTION NAME": "INSULIN SYRINGE 40 IU (per piece)",
        "Agreed price": 12.5
      },
      {
        "PRESCRIPTION NAME": "LOMOTIL (per tab)",
        "Agreed price": 12.5
      },
      {
        "PRESCRIPTION NAME": "METAPRIM 25MG (per tab)",
        "Agreed price": 12.5
      },
      {
        "PRESCRIPTION NAME": "METOCLOPRAMIDE 10MG (per tab)",
        "Agreed price": 12.5
      },
      {
        "PRESCRIPTION NAME": "Needle (per unit)",
        "Agreed price": 12.5
      },
      {
        "PRESCRIPTION NAME": "NITROFURANTOIN 100MG (per tab)",
        "Agreed price": 12.5
      },
      {
        "PRESCRIPTION NAME": "PREDNISOLONE 5MG (per tab)",
        "Agreed price": 12.5
      },
      {
        "PRESCRIPTION NAME": "STEMETIL 5MG (per tab)",
        "Agreed price": 12.5
      },
      {
        "PRESCRIPTION NAME": "TRIFLUOPERAZINE 5MG (per tab)",
        "Agreed price": 12.5
      },
      {
        "PRESCRIPTION NAME": "VIT B COMPLEX  (per tab)",
        "Agreed price": 12.5
      },
      {
        "PRESCRIPTION NAME": "VIT A TAB",
        "Agreed price": 13.75
      },
      {
        "PRESCRIPTION NAME": "CHLORPHENIRAMINE 4MG (per tab)",
        "Agreed price": 15
      },
      {
        "PRESCRIPTION NAME": "METRONIDAZOLE 200MG  (per tab)",
        "Agreed price": 15
      },
      {
        "PRESCRIPTION NAME": "PYRIDOXINE 50MG (per tab)",
        "Agreed price": 15
      },
      {
        "PRESCRIPTION NAME": "CAPTOPRIL 12.5MG (per tab)",
        "Agreed price": 18.75
      },
      {
        "PRESCRIPTION NAME": "CAPTOPRIL 50MG (per tab)",
        "Agreed price": 18.75
      },
      {
        "PRESCRIPTION NAME": "CHLOROQUINE 150MG (per tab)",
        "Agreed price": 18.75
      },
      {
        "PRESCRIPTION NAME": "CHLORPROMAZINE 100MG (per tab)",
        "Agreed price": 18.75
      },
      {
        "PRESCRIPTION NAME": "CIMETIDINE 200MG (per tab)",
        "Agreed price": 18.75
      },
      {
        "PRESCRIPTION NAME": "DIABETIN 450MG (per tab)",
        "Agreed price": 18.75
      },
      {
        "PRESCRIPTION NAME": "DIAMOX 250MG (per tab)",
        "Agreed price": 18.75
      },
      {
        "PRESCRIPTION NAME": "HYDROCORTISONE TABS 10MG",
        "Agreed price": 18.75
      },
      {
        "PRESCRIPTION NAME": "IBUPROFEN 200MG (per tab)",
        "Agreed price": 18.75
      },
      {
        "PRESCRIPTION NAME": "MEFENAMIC ACID 250MG (per tab)",
        "Agreed price": 18.75
      },
      {
        "PRESCRIPTION NAME": "MODURETIC (per tab)",
        "Agreed price": 18.75
      },
      {
        "PRESCRIPTION NAME": "NICOTINIC ACID (per tab)",
        "Agreed price": 18.75
      },
      {
        "PRESCRIPTION NAME": "NORMORETIC (per tab)",
        "Agreed price": 18.75
      },
      {
        "PRESCRIPTION NAME": "Retinol (Vit A) Caps (per cap)",
        "Agreed price": 18.75
      },
      {
        "PRESCRIPTION NAME": "DOXYCYCLINE (per cap)",
        "Agreed price": 20
      },
      {
        "PRESCRIPTION NAME": "METRONIDAZOLE 400MG (per tab)",
        "Agreed price": 20
      },
      {
        "PRESCRIPTION NAME": "TETRACYCLINE 250MG (per cap)",
        "Agreed price": 20
      },
      {
        "PRESCRIPTION NAME": "LIV 52 (PER TAB)",
        "Agreed price": 21.25
      },
      {
        "PRESCRIPTION NAME": "ACETAZOLAMIDE 250MG (per tab)",
        "Agreed price": 25
      },
      {
        "PRESCRIPTION NAME": "BENDROFLUAZIDE (per tab)",
        "Agreed price": 25
      },
      {
        "PRESCRIPTION NAME": "CANDERIL SWEETNER (per tab)",
        "Agreed price": 25
      },
      {
        "PRESCRIPTION NAME": "CIMETIDINE 400MG (per tab)",
        "Agreed price": 25
      },
      {
        "PRESCRIPTION NAME": "DEQUADIN LOZENGES (per tab)",
        "Agreed price": 25
      },
      {
        "PRESCRIPTION NAME": "ETHAMBUTOL 400MG (per tab)",
        "Agreed price": 25
      },
      {
        "PRESCRIPTION NAME": "FRANOL (per tab)",
        "Agreed price": 25
      },
      {
        "PRESCRIPTION NAME": "FRUSEMIDE 40MG (per tab)",
        "Agreed price": 25
      },
      {
        "PRESCRIPTION NAME": "GESTID (per tab)",
        "Agreed price": 25
      },
      {
        "PRESCRIPTION NAME": "GLIBENCLAMIDE 5MG (per tab)",
        "Agreed price": 25
      },
      {
        "PRESCRIPTION NAME": "HYOSCINE N BUTYL BROMIDE (per tab)",
        "Agreed price": 25
      },
      {
        "PRESCRIPTION NAME": "IBUFROPEN 400MG (per tab)",
        "Agreed price": 25
      },
      {
        "PRESCRIPTION NAME": "INDERAL 40MG (per tab)",
        "Agreed price": 25
      },
      {
        "PRESCRIPTION NAME": "RANFERON-12  (per tab)",
        "Agreed price": 25
      },
      {
        "PRESCRIPTION NAME": "ROVIGON (per tab)",
        "Agreed price": 25
      },
      {
        "PRESCRIPTION NAME": "ENALAPRIL 5MG TAB",
        "Agreed price": 26.25
      },
      {
        "PRESCRIPTION NAME": "AMPICILLIN 250MG (PER TAB)",
        "Agreed price": 30
      },
      {
        "PRESCRIPTION NAME": "DIAZEPAM 5MG (per tab)",
        "Agreed price": 30
      },
      {
        "PRESCRIPTION NAME": "HAEMORON (PER TAB)",
        "Agreed price": 30
      },
      {
        "PRESCRIPTION NAME": "PROPANOLOL 40MG (per tab)",
        "Agreed price": 30
      },
      {
        "PRESCRIPTION NAME": "PYRAZINAMIDE 500MG (per tab)",
        "Agreed price": 30
      },
      {
        "PRESCRIPTION NAME": "ACTIFED  (per tab)",
        "Agreed price": 31.25
      },
      {
        "PRESCRIPTION NAME": "APRESOLINE 25MG  (per tab)",
        "Agreed price": 31.25
      },
      {
        "PRESCRIPTION NAME": "CARVEDILOL 6.25mg (PER TAB)",
        "Agreed price": 31.25
      },
      {
        "PRESCRIPTION NAME": "ETOVIT CAPGEL 200MG (per cap)",
        "Agreed price": 31.25
      },
      {
        "PRESCRIPTION NAME": "EVITOL 100MG (per tab)",
        "Agreed price": 31.25
      },
      {
        "PRESCRIPTION NAME": "ISORDIL 5MG (per tab)",
        "Agreed price": 31.25
      },
      {
        "PRESCRIPTION NAME": "CHLORPHENIRAMINE INJ (PER AMP)",
        "Agreed price": 32.5
      },
      {
        "PRESCRIPTION NAME": "ASPIRIN 300MG (per tab)",
        "Agreed price": 35
      },
      {
        "PRESCRIPTION NAME": "CO-TRIMAZOLE 240MG/5ML (per bot)",
        "Agreed price": 35
      },
      {
        "PRESCRIPTION NAME": "DIGOXIN 0.25MG (per tab)",
        "Agreed price": 35
      },
      {
        "PRESCRIPTION NAME": "GRISEOFULVIN 125MG (per tab)",
        "Agreed price": 35
      },
      {
        "PRESCRIPTION NAME": "ABITREN 100MG (per tab)",
        "Agreed price": 37.5
      },
      {
        "PRESCRIPTION NAME": "Aldactone",
        "Agreed price": 37.5
      },
      {
        "PRESCRIPTION NAME": "ANOROL  (per tab)",
        "Agreed price": 37.5
      },
      {
        "PRESCRIPTION NAME": "CARBAMAZEPINE  200MG (per tab)",
        "Agreed price": 37.5
      },
      {
        "PRESCRIPTION NAME": "CHYMORAL (per tab)",
        "Agreed price": 37.5
      },
      {
        "PRESCRIPTION NAME": "CO-TRIMAZOLE 480MG (per tab)",
        "Agreed price": 37.5
      },
      {
        "PRESCRIPTION NAME": "Ergocalciferol (Vit D) Tabs (per tab)",
        "Agreed price": 37.5
      },
      {
        "PRESCRIPTION NAME": "EVENNG PRIME ROSE (per cap)",
        "Agreed price": 37.5
      },
      {
        "PRESCRIPTION NAME": "INSULIN SYRINGE 100 IU (per piece)",
        "Agreed price": 37.5
      },
      {
        "PRESCRIPTION NAME": "ISORDIL 10MG (per tab)",
        "Agreed price": 37.5
      },
      {
        "PRESCRIPTION NAME": "KOTASE (per tab)",
        "Agreed price": 37.5
      },
      {
        "PRESCRIPTION NAME": "LEXOTHAN 1.5MG (per tab)",
        "Agreed price": 37.5
      },
      {
        "PRESCRIPTION NAME": "LINCOMYCIN 500MG (per cap)",
        "Agreed price": 37.5
      },
      {
        "PRESCRIPTION NAME": "LISINOPRIL 5MG (per tab)",
        "Agreed price": 37.5
      },
      {
        "PRESCRIPTION NAME": "MAXOLON (PER TAB)",
        "Agreed price": 37.5
      },
      {
        "PRESCRIPTION NAME": "NIFEGEM RETARD 20MG (per tab)",
        "Agreed price": 37.5
      },
      {
        "PRESCRIPTION NAME": "NIVAQUINE FORTE CAP (per cap)",
        "Agreed price": 37.5
      },
      {
        "PRESCRIPTION NAME": "WARFRIN SODIUM 5MG (per tab)",
        "Agreed price": 37.5
      },
      {
        "PRESCRIPTION NAME": "AMITRIPTYLINE 25MG (per tab)",
        "Agreed price": 40
      },
      {
        "PRESCRIPTION NAME": "AMOXYCILLIN  250MG (per cap)",
        "Agreed price": 40
      },
      {
        "PRESCRIPTION NAME": "DICLOFENAC 50MG (per tab)",
        "Agreed price": 40
      },
      {
        "PRESCRIPTION NAME": "LORATIDINE 10MG (per tab)",
        "Agreed price": 40
      },
      {
        "PRESCRIPTION NAME": "THALAZOLE 500MG (per tab)",
        "Agreed price": 40
      },
      {
        "PRESCRIPTION NAME": "ZINC 30MG TAB",
        "Agreed price": 40
      },
      {
        "PRESCRIPTION NAME": "SIMVASTATIN 20MG TAB",
        "Agreed price": 41.25
      },
      {
        "PRESCRIPTION NAME": "COTENIDONE TABS (per tab)",
        "Agreed price": 42.5
      },
      {
        "PRESCRIPTION NAME": "OLANZAPINE 5MG (per tab)",
        "Agreed price": 42.5
      },
      {
        "PRESCRIPTION NAME": "Bisoprolol 2.5mg",
        "Agreed price": 43.75
      },
      {
        "PRESCRIPTION NAME": "CO-PROXAMOL (per tab)",
        "Agreed price": 43.75
      },
      {
        "PRESCRIPTION NAME": "ENCEPHABOL (per tab)",
        "Agreed price": 43.75
      },
      {
        "PRESCRIPTION NAME": "MOTILIUM 10MG (per tab)",
        "Agreed price": 43.75
      },
      {
        "PRESCRIPTION NAME": "NEOMERCAZOLE 5MG (per tab)",
        "Agreed price": 43.75
      },
      {
        "PRESCRIPTION NAME": "ERYTHROMYCIN 250MG (per tab)",
        "Agreed price": 45
      },
      {
        "PRESCRIPTION NAME": "GLUCOPHAGE 850MG (PER TAB)",
        "Agreed price": 45
      },
      {
        "PRESCRIPTION NAME": "HYDROCHLORTIAZIDE 50MG/AMILORIDE 5MG(per tab",
        "Agreed price": 45
      },
      {
        "PRESCRIPTION NAME": "HYDROCHLOROTHIAZIDE 25MG",
        "Agreed price": 45
      },
      {
        "PRESCRIPTION NAME": "KETOCONAZOLE 200MG (per tab)",
        "Agreed price": 45
      },
      {
        "PRESCRIPTION NAME": "METHYL DOPA 250MG(ALDOMET) (per tab)",
        "Agreed price": 45
      },
      {
        "PRESCRIPTION NAME": "PHENOBARBITONE 30MG (per tab)",
        "Agreed price": 45
      },
      {
        "PRESCRIPTION NAME": "Syringe & Needle 10ml (per unit)",
        "Agreed price": 45
      },
      {
        "PRESCRIPTION NAME": "Syringe & Needle 2ml (per unit)",
        "Agreed price": 45
      },
      {
        "PRESCRIPTION NAME": "Syringe & Needle 5ml (per unit)",
        "Agreed price": 45
      },
      {
        "PRESCRIPTION NAME": "TABALON 400MG (per tab)",
        "Agreed price": 45
      },
      {
        "PRESCRIPTION NAME": "CEPHALEXIN (PER CAP)",
        "Agreed price": 48.75
      },
      {
        "PRESCRIPTION NAME": "XTAPEN (PER AMP)",
        "Agreed price": 48.75
      },
      {
        "PRESCRIPTION NAME": "ALLOPURINOL 100MG TAB",
        "Agreed price": 50
      },
      {
        "PRESCRIPTION NAME": "AMOXYCILLIN  500MG (per cap)",
        "Agreed price": 50
      },
      {
        "PRESCRIPTION NAME": "BRINERDINE (per tab)",
        "Agreed price": 50
      },
      {
        "PRESCRIPTION NAME": "CHLORPROPAMIDE 250MG (per tab)",
        "Agreed price": 50
      },
      {
        "PRESCRIPTION NAME": "DICLOFENAC 100MG (per tab)",
        "Agreed price": 50
      },
      {
        "PRESCRIPTION NAME": "LEXOTHAN 3MG  (per tab)",
        "Agreed price": 50
      },
      {
        "PRESCRIPTION NAME": "LISINOPRIL 10MG (per tab)",
        "Agreed price": 50
      },
      {
        "PRESCRIPTION NAME": "NITRAZEPAM 5MG (per tab)",
        "Agreed price": 50
      },
      {
        "PRESCRIPTION NAME": "OBRON 6 CAP (per cap)",
        "Agreed price": 50
      },
      {
        "PRESCRIPTION NAME": "VIT C INJ (per amp)",
        "Agreed price": 50
      },
      {
        "PRESCRIPTION NAME": "ATOVASTATIN 10MG (PER TAB)",
        "Agreed price": 52.5
      },
      {
        "PRESCRIPTION NAME": "ATENOLOL 100MG (per tab)",
        "Agreed price": 53
      },
      {
        "PRESCRIPTION NAME": "ATENOLOL 50MG (per tab)",
        "Agreed price": 53
      },
      {
        "PRESCRIPTION NAME": "QUININE 300MG (per tab)",
        "Agreed price": 55
      },
      {
        "PRESCRIPTION NAME": "Mesterolone Tabs 25mg (per tab)",
        "Agreed price": 56.25
      },
      {
        "PRESCRIPTION NAME": "ASTYMIN (PER CAP).",
        "Agreed price": 57.5
      },
      {
        "PRESCRIPTION NAME": "CAPTOPRIL 25MG (per tab)",
        "Agreed price": 60
      },
      {
        "PRESCRIPTION NAME": "DIHYDROCODEINE 30MG (per tab)",
        "Agreed price": 60
      },
      {
        "PRESCRIPTION NAME": "GLUCOPHAGE 500MG (per tab)",
        "Agreed price": 60
      },
      {
        "PRESCRIPTION NAME": "KETRAX (PER TAB).",
        "Agreed price": 60
      },
      {
        "PRESCRIPTION NAME": "LOSARTAN 50MG PER TAB",
        "Agreed price": 60
      },
      {
        "PRESCRIPTION NAME": "NIFEDIPINE 20MG (per tab)",
        "Agreed price": 60
      },
      {
        "PRESCRIPTION NAME": "Syringe & Needle 20ml (per unit)",
        "Agreed price": 60
      },
      {
        "PRESCRIPTION NAME": "CHLOROQUINE 200MG (per amp)",
        "Agreed price": 62.5
      },
      {
        "PRESCRIPTION NAME": "CORDARONE 200MG (per tab)",
        "Agreed price": 62.5
      },
      {
        "PRESCRIPTION NAME": "DITROPAN 5MG (per tab)",
        "Agreed price": 62.5
      },
      {
        "PRESCRIPTION NAME": "DYRIDAMOLE 100MG TAB",
        "Agreed price": 62.5
      },
      {
        "PRESCRIPTION NAME": "Ergocalciferol (Vit D) Solution (per amp)",
        "Agreed price": 62.5
      },
      {
        "PRESCRIPTION NAME": "ERGOMETRINE 0.5MG (PER TAB)",
        "Agreed price": 62.5
      },
      {
        "PRESCRIPTION NAME": "FERROBIN",
        "Agreed price": 62.5
      },
      {
        "PRESCRIPTION NAME": "GRISEOFULVIN 500MG (per tab)",
        "Agreed price": 62.5
      },
      {
        "PRESCRIPTION NAME": "MANIX  (per tab)",
        "Agreed price": 62.5
      },
      {
        "PRESCRIPTION NAME": "MOSEGOR 0.5MG (per tab)",
        "Agreed price": 62.5
      },
      {
        "PRESCRIPTION NAME": "NORFLEX TABS (per tab)",
        "Agreed price": 62.5
      },
      {
        "PRESCRIPTION NAME": "NORGESIC TAB",
        "Agreed price": 62.5
      },
      {
        "PRESCRIPTION NAME": "OMEGA H3  (per cap)",
        "Agreed price": 62.5
      },
      {
        "PRESCRIPTION NAME": "PALUDRINE 100MG TAB (per tab)",
        "Agreed price": 62.5
      },
      {
        "PRESCRIPTION NAME": "STUGERON  25MG (per tab)",
        "Agreed price": 62.5
      },
      {
        "PRESCRIPTION NAME": "Testosterone Inj 200mg/ml (per amp)",
        "Agreed price": 62.5
      },
      {
        "PRESCRIPTION NAME": "ALAXIN- P (PER TAB)",
        "Agreed price": 65
      },
      {
        "PRESCRIPTION NAME": "ALLOPURINOL 200MG TAB",
        "Agreed price": 65
      },
      {
        "PRESCRIPTION NAME": "ARTEMETHER/LUMEFANTRINE 20/120 (PER TABLET)",
        "Agreed price": 65
      },
      {
        "PRESCRIPTION NAME": "LIVOLIN FORTE TABS (per tab)",
        "Agreed price": 67.5
      },
      {
        "PRESCRIPTION NAME": "PERSANTIN (PER TAB)",
        "Agreed price": 67.5
      },
      {
        "PRESCRIPTION NAME": "AMPICLOX 500MG CAP (per cap)",
        "Agreed price": 70
      },
      {
        "PRESCRIPTION NAME": "Sirdalud 2mg",
        "Agreed price": 70
      },
      {
        "PRESCRIPTION NAME": "Bisoprolol 5mg",
        "Agreed price": 75
      },
      {
        "PRESCRIPTION NAME": "BROMHEXINE 8MG (per tab)",
        "Agreed price": 75
      },
      {
        "PRESCRIPTION NAME": "COMBANTRIN 125MG (per tab)",
        "Agreed price": 75
      },
      {
        "PRESCRIPTION NAME": "DIPYRIDAMOLE (PER TAB)",
        "Agreed price": 75
      },
      {
        "PRESCRIPTION NAME": "EVITOL100MG CAPGEL (per cap)",
        "Agreed price": 75
      },
      {
        "PRESCRIPTION NAME": "HISTAC  150MG (per tab)",
        "Agreed price": 75
      },
      {
        "PRESCRIPTION NAME": "HOMTAMIN GINSENG (per tab)",
        "Agreed price": 75
      },
      {
        "PRESCRIPTION NAME": "HYPOVASE 1MG (per tab)",
        "Agreed price": 75
      },
      {
        "PRESCRIPTION NAME": "Lexotan Inj",
        "Agreed price": 75
      },
      {
        "PRESCRIPTION NAME": "OCUVITE (per tab)",
        "Agreed price": 75
      },
      {
        "PRESCRIPTION NAME": "PEFLOXACIN 400MG (per tab)",
        "Agreed price": 75
      },
      {
        "PRESCRIPTION NAME": "PHENYTOIN 100MG (per cap)",
        "Agreed price": 75
      },
      {
        "PRESCRIPTION NAME": "PROVIRON 25 MG (per tab)",
        "Agreed price": 75
      },
      {
        "PRESCRIPTION NAME": "REGROTON (per tab)",
        "Agreed price": 75
      },
      {
        "PRESCRIPTION NAME": "SANATOGEN M/VIT GOLD (per tab)",
        "Agreed price": 75
      },
      {
        "PRESCRIPTION NAME": "TAVEGYL 1MG (per tab)",
        "Agreed price": 75
      },
      {
        "PRESCRIPTION NAME": "VIT E 1000 IU NATURE MADE (per tab)",
        "Agreed price": 75
      },
      {
        "PRESCRIPTION NAME": "ARTHROTEC (PER TAB)",
        "Agreed price": 77.5
      },
      {
        "PRESCRIPTION NAME": "AMLODIPINE 5MG (PER TAB)",
        "Agreed price": 80
      },
      {
        "PRESCRIPTION NAME": "GLUCOPHAGE 1G (per tab)",
        "Agreed price": 80
      },
      {
        "PRESCRIPTION NAME": "Scalp Vein Needle (per unit)",
        "Agreed price": 80
      },
      {
        "PRESCRIPTION NAME": "ARTESUNATE 100MG (PER TAB)",
        "Agreed price": 81.25
      },
      {
        "PRESCRIPTION NAME": "CAMOQUINE 200MG (per tab)",
        "Agreed price": 81.25
      },
      {
        "PRESCRIPTION NAME": "DICYNONE 250MG (per tab)",
        "Agreed price": 81.25
      },
      {
        "PRESCRIPTION NAME": "FASIGYN 500MG (per tab)",
        "Agreed price": 81.25
      },
      {
        "PRESCRIPTION NAME": "IMMUNACE (per tab)",
        "Agreed price": 81.25
      },
      {
        "PRESCRIPTION NAME": "LO-FEMINAL (per sach)",
        "Agreed price": 81.25
      },
      {
        "PRESCRIPTION NAME": "ROXITHROMYCIN TABS (per tab)",
        "Agreed price": 81.25
      },
      {
        "PRESCRIPTION NAME": "SULPHADEINE PLUS SOLUBLE (per tab)",
        "Agreed price": 81.25
      },
      {
        "PRESCRIPTION NAME": "Cyanocobalamin (B12) Inj (per amp)",
        "Agreed price": 87.5
      },
      {
        "PRESCRIPTION NAME": "FLOXAPEN 125MG/5ML (per cap)",
        "Agreed price": 87.5
      },
      {
        "PRESCRIPTION NAME": "OSTEOCARE (per tab)",
        "Agreed price": 87.5
      },
      {
        "PRESCRIPTION NAME": "Vit B Complex Inj (per vial)",
        "Agreed price": 87.5
      },
      {
        "PRESCRIPTION NAME": "DICLOFENAC SUPP 100MG (PER SUPP)",
        "Agreed price": 90
      },
      {
        "PRESCRIPTION NAME": "GLICAZIDE 80MG (PER TAB)",
        "Agreed price": 90
      },
      {
        "PRESCRIPTION NAME": "METHYL DOPA 500MG(ALDOMET) (per tab)",
        "Agreed price": 90
      },
      {
        "PRESCRIPTION NAME": "RANITHIDINE 150MG (per tab)",
        "Agreed price": 90
      },
      {
        "PRESCRIPTION NAME": "Rosuvastatin 5MG",
        "Agreed price": 90
      },
      {
        "PRESCRIPTION NAME": "Bisoprolol 10mg",
        "Agreed price": 93.75
      },
      {
        "PRESCRIPTION NAME": "NEUROBION (per tab)",
        "Agreed price": 93.75
      },
      {
        "PRESCRIPTION NAME": "DOLONUEROBION (per tab)",
        "Agreed price": 95
      },
      {
        "PRESCRIPTION NAME": "SPIRONOLACTONE 25MG (per tab)",
        "Agreed price": 95
      },
      {
        "PRESCRIPTION NAME": "PIOGLITAZONE HCL 30MG (PER TAB).",
        "Agreed price": 97
      },
      {
        "PRESCRIPTION NAME": "CHLORAMPHENICOL 500MG INJ/ AMP",
        "Agreed price": 97.5
      },
      {
        "PRESCRIPTION NAME": "ACARBOSE 50MG (PER TAB)",
        "Agreed price": 100
      },
      {
        "PRESCRIPTION NAME": "ACICLOVIR 200MG (per tab)",
        "Agreed price": 100
      },
      {
        "PRESCRIPTION NAME": "AMLODIPINE 10MG (per tab)",
        "Agreed price": 100
      },
      {
        "PRESCRIPTION NAME": "ARTHOCARE CAP (per tab)",
        "Agreed price": 100
      },
      {
        "PRESCRIPTION NAME": "CAC 1000 (per tab)",
        "Agreed price": 100
      },
      {
        "PRESCRIPTION NAME": "CIPROTAB 500MG (per tab)",
        "Agreed price": 100
      },
      {
        "PRESCRIPTION NAME": "CLONIDINE 100MCG (per tab)",
        "Agreed price": 100
      },
      {
        "PRESCRIPTION NAME": "GERIATIC PHARMATON (per cap)",
        "Agreed price": 100
      },
      {
        "PRESCRIPTION NAME": "Infusion Set (per unit)",
        "Agreed price": 100
      },
      {
        "PRESCRIPTION NAME": "NAPROXEN 500MG (PER TAB)",
        "Agreed price": 100
      },
      {
        "PRESCRIPTION NAME": "NATRILIX (PER TAB)",
        "Agreed price": 100
      },
      {
        "PRESCRIPTION NAME": "Ofloxacin Caps 200mg (per cap)",
        "Agreed price": 100
      },
      {
        "PRESCRIPTION NAME": "OMEPRAZOLE 20MG (PER TAB).",
        "Agreed price": 100
      },
      {
        "PRESCRIPTION NAME": "PIROXICAM 20MG (per cap)",
        "Agreed price": 100
      },
      {
        "PRESCRIPTION NAME": "PRAZIQUANTEL 600MG (per tab)",
        "Agreed price": 100
      },
      {
        "PRESCRIPTION NAME": "Sirdalud 4mg",
        "Agreed price": 100
      },
      {
        "PRESCRIPTION NAME": "THYROXINE 0.5MG (per tab)",
        "Agreed price": 100
      },
      {
        "PRESCRIPTION NAME": "GLIPIZIDE 5MG (PER TAB)",
        "Agreed price": 105
      },
      {
        "PRESCRIPTION NAME": "MAXIVISION  (per cap)",
        "Agreed price": 106.25
      },
      {
        "PRESCRIPTION NAME": "ZADITEN 1MG (per tab)",
        "Agreed price": 106.25
      },
      {
        "PRESCRIPTION NAME": "CLOPIDOGREL(PER TAB)",
        "Agreed price": 112.5
      },
      {
        "PRESCRIPTION NAME": "MINIZIDE (per tab)",
        "Agreed price": 112.5
      },
      {
        "PRESCRIPTION NAME": "CIMETIDINE INJ PER AMP",
        "Agreed price": 113.75
      },
      {
        "PRESCRIPTION NAME": "GABAPENTRIN(PER TAB)",
        "Agreed price": 113.75
      },
      {
        "PRESCRIPTION NAME": "SUFFRATULE(PER PIECE)",
        "Agreed price": 113.75
      },
      {
        "PRESCRIPTION NAME": "CAMOSUNATE 600/200 (PER TAB)",
        "Agreed price": 120
      },
      {
        "PRESCRIPTION NAME": "CIPROFLOXACIN 500MG (PER TAB)",
        "Agreed price": 120
      },
      {
        "PRESCRIPTION NAME": "Rosuvastatin 10MG",
        "Agreed price": 120
      },
      {
        "PRESCRIPTION NAME": "ALPHABETHIC CAPLET (per tab)",
        "Agreed price": 125
      },
      {
        "PRESCRIPTION NAME": "DAFLON (per tab)",
        "Agreed price": 125
      },
      {
        "PRESCRIPTION NAME": "DEXAMETHASONE 8MG  (per vial)",
        "Agreed price": 125
      },
      {
        "PRESCRIPTION NAME": "DYNAMOGEN LIQUID 10MLS (per bot)",
        "Agreed price": 125
      },
      {
        "PRESCRIPTION NAME": "EUCADIC 3.125MG (per tab)",
        "Agreed price": 125
      },
      {
        "PRESCRIPTION NAME": "HISTAC 300MG (per tab)",
        "Agreed price": 125
      },
      {
        "PRESCRIPTION NAME": "IMODIUM 4MG (per tab)",
        "Agreed price": 125
      },
      {
        "PRESCRIPTION NAME": "MEPRASIL 20MG (per cap)",
        "Agreed price": 125
      },
      {
        "PRESCRIPTION NAME": "NOSPA TABS 40MG (per tab)",
        "Agreed price": 125
      },
      {
        "PRESCRIPTION NAME": "ORUVAIL 200MG (per cap)",
        "Agreed price": 125
      },
      {
        "PRESCRIPTION NAME": "TAMSULOSIN(PER TAB)",
        "Agreed price": 125
      },
      {
        "PRESCRIPTION NAME": "TEGRETOL 200MG (per tab)",
        "Agreed price": 125
      },
      {
        "PRESCRIPTION NAME": "THROXINE 100MCG (per tab)",
        "Agreed price": 125
      },
      {
        "PRESCRIPTION NAME": "STREPSIL LOZENGES (per tab)",
        "Agreed price": 128
      },
      {
        "PRESCRIPTION NAME": "NIZORAL 200MG (per tab)",
        "Agreed price": 131.25
      },
      {
        "PRESCRIPTION NAME": "SPARFLOXACIN 200MG (per tab)",
        "Agreed price": 131.25
      },
      {
        "PRESCRIPTION NAME": "VOLTAREN RETARD 100MG (per tab)",
        "Agreed price": 131.25
      },
      {
        "PRESCRIPTION NAME": "CHLOROQUINE 50MG/5ML (per bot)",
        "Agreed price": 137.5
      },
      {
        "PRESCRIPTION NAME": "SALBUTAMOL NEBULES 2.5MG (per neb)",
        "Agreed price": 137.5
      },
      {
        "PRESCRIPTION NAME": "ACTIVATED CHARCOAL (per cap)",
        "Agreed price": 140
      },
      {
        "PRESCRIPTION NAME": "BENZHEXOL 5MG (per tab)",
        "Agreed price": 140
      },
      {
        "PRESCRIPTION NAME": "IV Cannula (per unit)",
        "Agreed price": 140
      },
      {
        "PRESCRIPTION NAME": "RABEPRAZOLE 20MG (per tab)",
        "Agreed price": 140
      },
      {
        "PRESCRIPTION NAME": "DICLOFENAC SUPP 12.5MG (PER SUPP)",
        "Agreed price": 147.5
      },
      {
        "PRESCRIPTION NAME": "Amaryl 2mg",
        "Agreed price": 150
      },
      {
        "PRESCRIPTION NAME": "AMOXYL+CLAVULANIC ACID 375MG TAB (PER TAB)",
        "Agreed price": 150
      },
      {
        "PRESCRIPTION NAME": "Ascorbic Acid (Vit C) Syrup (per bot.)",
        "Agreed price": 150
      },
      {
        "PRESCRIPTION NAME": "Dextromethorphan Hydrobromide Syrup (per bot.",
        "Agreed price": 150
      },
      {
        "PRESCRIPTION NAME": "FANSIDAR 525MG (per tab)",
        "Agreed price": 150
      },
      {
        "PRESCRIPTION NAME": "FRUSEMIDE INJ 20MG (per amp)",
        "Agreed price": 150
      },
      {
        "PRESCRIPTION NAME": "GENTAMYCIN 80MG (per amp)",
        "Agreed price": 150
      },
      {
        "PRESCRIPTION NAME": "HYOSCINE N BUTYL BROMIDE 20MG (per amp)",
        "Agreed price": 150
      },
      {
        "PRESCRIPTION NAME": "Levetiractam 250mg(Keppra)",
        "Agreed price": 150
      },
      {
        "PRESCRIPTION NAME": "LEVOFLOXACIN TAB 500MG",
        "Agreed price": 150
      },
      {
        "PRESCRIPTION NAME": "MINIPRESS 1MG (per tab)",
        "Agreed price": 150
      },
      {
        "PRESCRIPTION NAME": "Neuracalm",
        "Agreed price": 150
      },
      {
        "PRESCRIPTION NAME": "PRIMOLUT N 5MG (per tab)",
        "Agreed price": 150
      },
      {
        "PRESCRIPTION NAME": "RANITHIDINE 300MG (per tab)",
        "Agreed price": 150
      },
      {
        "PRESCRIPTION NAME": "ROHYPNOL 1MG (per tab)",
        "Agreed price": 150
      },
      {
        "PRESCRIPTION NAME": "Sertraline 50MG (per cap)",
        "Agreed price": 150
      },
      {
        "PRESCRIPTION NAME": "TELMISARTAN 80MG",
        "Agreed price": 150
      },
      {
        "PRESCRIPTION NAME": "VITAMIN A DROPS",
        "Agreed price": 150
      },
      {
        "PRESCRIPTION NAME": "PROGUANIL 100MG (per tab)",
        "Agreed price": 156.25
      },
      {
        "PRESCRIPTION NAME": "ALBENDAZOLE (PER TAB)",
        "Agreed price": 162.5
      },
      {
        "PRESCRIPTION NAME": "CHLORAMPHENICOL EYE OINT. (per tube)",
        "Agreed price": 162.5
      },
      {
        "PRESCRIPTION NAME": "INFERON (PER AMP)",
        "Agreed price": 162.5
      },
      {
        "PRESCRIPTION NAME": "METAKELFIN (per tab)",
        "Agreed price": 162.5
      },
      {
        "PRESCRIPTION NAME": "SECWID 400MG (PER TAB)",
        "Agreed price": 162.5
      },
      {
        "PRESCRIPTION NAME": "Sodium vaporate (epilium 200mg)",
        "Agreed price": 162.5
      },
      {
        "PRESCRIPTION NAME": "STREPTOMYCIN 5MG INJ (per vial)",
        "Agreed price": 162.5
      },
      {
        "PRESCRIPTION NAME": "ZADITEN 2MG (per tab)",
        "Agreed price": 162.5
      },
      {
        "PRESCRIPTION NAME": "SECNIDAZOLE 500MG(PER TAB)",
        "Agreed price": 170
      },
      {
        "PRESCRIPTION NAME": "ESSENTIAL FORTE CAP (per cap)",
        "Agreed price": 175
      },
      {
        "PRESCRIPTION NAME": "Pregabalin 75mg",
        "Agreed price": 175
      },
      {
        "PRESCRIPTION NAME": "NYSTATIN PESSARIES (PER TAB)",
        "Agreed price": 180
      },
      {
        "PRESCRIPTION NAME": "CARFERGOT 50MG (per tab)",
        "Agreed price": 187.5
      },
      {
        "PRESCRIPTION NAME": "CLOMID 50MG (per tab)",
        "Agreed price": 187.5
      },
      {
        "PRESCRIPTION NAME": "EUCARDIC 25MG (per tab)",
        "Agreed price": 187.5
      },
      {
        "PRESCRIPTION NAME": "Labetalol 100mg",
        "Agreed price": 187.5
      },
      {
        "PRESCRIPTION NAME": "TRAMADOL 50MG (per cap)",
        "Agreed price": 187.5
      },
      {
        "PRESCRIPTION NAME": "CLINDAMYCIN HCL 300MG CAP (per cap)",
        "Agreed price": 192.5
      },
      {
        "PRESCRIPTION NAME": "AMOXYL+CLAVULANIC ACID 625MG TAB (PER TAB)",
        "Agreed price": 200
      },
      {
        "PRESCRIPTION NAME": "BROMOCRIPTINE 2.5MG (per tab)",
        "Agreed price": 200
      },
      {
        "PRESCRIPTION NAME": "CALAMINE LOTION  100MLS (per bot)",
        "Agreed price": 200
      },
      {
        "PRESCRIPTION NAME": "CRYSTALLINE PENICILLIN (PER AMPOULE)",
        "Agreed price": 200
      },
      {
        "PRESCRIPTION NAME": "DIGOXIN 0.025MG INL (PER AMP)",
        "Agreed price": 200
      },
      {
        "PRESCRIPTION NAME": "FLUCONAZOLE 50MG (PER TAB)",
        "Agreed price": 200
      },
      {
        "PRESCRIPTION NAME": "Iron Dextran Inj 50mg/2ml (per amp)",
        "Agreed price": 200
      },
      {
        "PRESCRIPTION NAME": "METOCLOPRAMIDE 5MG INJ (per amp)",
        "Agreed price": 200
      },
      {
        "PRESCRIPTION NAME": "Nasogastric (NG) TUbe",
        "Agreed price": 200
      },
      {
        "PRESCRIPTION NAME": "ORAL REHYDRATION SALT",
        "Agreed price": 200
      },
      {
        "PRESCRIPTION NAME": "PARACETAMOL 125MG  SUPPOSITORY",
        "Agreed price": 200
      },
      {
        "PRESCRIPTION NAME": "Paracetamol Inj (per amp)",
        "Agreed price": 200
      },
      {
        "PRESCRIPTION NAME": "Piroxicam inj.",
        "Agreed price": 200
      },
      {
        "PRESCRIPTION NAME": "PREGNACARE (per cap)",
        "Agreed price": 200
      },
      {
        "PRESCRIPTION NAME": "Rosuvastatin 20MG",
        "Agreed price": 200
      },
      {
        "PRESCRIPTION NAME": "UNASYN (PER TAB)",
        "Agreed price": 200
      },
      {
        "PRESCRIPTION NAME": "URINE BAG",
        "Agreed price": 200
      },
      {
        "PRESCRIPTION NAME": "CHLORAMPHENICOL EAR DROP (per bot)",
        "Agreed price": 212.5
      },
      {
        "PRESCRIPTION NAME": "Co-Aprovel 150mg (1Tab)",
        "Agreed price": 212.5
      },
      {
        "PRESCRIPTION NAME": "CO-MICARDIL (PER TAB)",
        "Agreed price": 218.75
      },
      {
        "PRESCRIPTION NAME": "CLARITHROMYCIN 500MG (per cap)",
        "Agreed price": 220
      },
      {
        "PRESCRIPTION NAME": "DUPHASON 10MG (per tab)",
        "Agreed price": 225
      },
      {
        "PRESCRIPTION NAME": "MIST KAOLIN (per bot)",
        "Agreed price": 225
      },
      {
        "PRESCRIPTION NAME": "PAROXETIN 100MG(PER TAB)",
        "Agreed price": 225
      },
      {
        "PRESCRIPTION NAME": "ATROPINE 6OOMG INJ (per amp)",
        "Agreed price": 237.5
      },
      {
        "PRESCRIPTION NAME": "CO-DIOVAN (per tab)",
        "Agreed price": 237.5
      },
      {
        "PRESCRIPTION NAME": "DIOVAN 80MG (per cap)",
        "Agreed price": 237.5
      },
      {
        "PRESCRIPTION NAME": "ITRANOX 100MG (per tab)",
        "Agreed price": 237.5
      },
      {
        "PRESCRIPTION NAME": "PEFLACINE 400MG (per tab)",
        "Agreed price": 237.5
      },
      {
        "PRESCRIPTION NAME": "CHLORAMPHENICOL SYRUP",
        "Agreed price": 242.5
      },
      {
        "PRESCRIPTION NAME": "CHLORAMPHENICOL EYE DROP (per bot)",
        "Agreed price": 243.75
      },
      {
        "PRESCRIPTION NAME": "HYDROXYPREGESTERONE (PER TAB)",
        "Agreed price": 243.75
      },
      {
        "PRESCRIPTION NAME": "LESCOL 20MG (per cap)",
        "Agreed price": 243.75
      },
      {
        "PRESCRIPTION NAME": "SALBUTAMOL NEBULES 5MG (per neb)",
        "Agreed price": 243.75
      },
      {
        "PRESCRIPTION NAME": "TENORETIC  (per tab)",
        "Agreed price": 243.75
      },
      {
        "PRESCRIPTION NAME": "WHITFIELD OINTMENT 20G (per tube)",
        "Agreed price": 243.75
      },
      {
        "PRESCRIPTION NAME": "Amaryl 4mg",
        "Agreed price": 250
      },
      {
        "PRESCRIPTION NAME": "Blood Giving Set (per unit)",
        "Agreed price": 250
      },
      {
        "PRESCRIPTION NAME": "CARVEDILOL 25mg(PER TAB)",
        "Agreed price": 250
      },
      {
        "PRESCRIPTION NAME": "CEFUROXIME 500MG TAB",
        "Agreed price": 250
      },
      {
        "PRESCRIPTION NAME": "Co-Aprovel 300mg (1Tab)",
        "Agreed price": 250
      },
      {
        "PRESCRIPTION NAME": "CO-CODAMOL 500MG",
        "Agreed price": 250
      },
      {
        "PRESCRIPTION NAME": "DETRUSITOL 2MG (per tab)",
        "Agreed price": 250
      },
      {
        "PRESCRIPTION NAME": "DIAMICRON 60mg (per tab)",
        "Agreed price": 250
      },
      {
        "PRESCRIPTION NAME": "DULCOLAX SUPP (PER SUPP)",
        "Agreed price": 250
      },
      {
        "PRESCRIPTION NAME": "FOLIC ACID SYRUP",
        "Agreed price": 250
      },
      {
        "PRESCRIPTION NAME": "GLYCERYLTRINITRATE (PER TAB)",
        "Agreed price": 250
      },
      {
        "PRESCRIPTION NAME": "GYNODAKTARIN 200MG (per ovule)",
        "Agreed price": 250
      },
      {
        "PRESCRIPTION NAME": "Labetalol 400mg",
        "Agreed price": 250
      },
      {
        "PRESCRIPTION NAME": "OXYTOCIN 10MG INJ PER AMP",
        "Agreed price": 250
      },
      {
        "PRESCRIPTION NAME": "PROMETHAZINE 50MG INJ (per amp)",
        "Agreed price": 250
      },
      {
        "PRESCRIPTION NAME": "QUININE INJ 300MG",
        "Agreed price": 250
      },
      {
        "PRESCRIPTION NAME": "SLOW-K 600MG (per tab)",
        "Agreed price": 250
      },
      {
        "PRESCRIPTION NAME": "TRANEXAMIC ACID 500mg (PER TAB)",
        "Agreed price": 250
      },
      {
        "PRESCRIPTION NAME": "MECTIZAN (IVERMECTIN) 3MG (per tab)",
        "Agreed price": 262.5
      },
      {
        "PRESCRIPTION NAME": "COFEX SYRUP (PER BOT)",
        "Agreed price": 276.25
      },
      {
        "PRESCRIPTION NAME": "ABAKTAL 400MG (per amp)",
        "Agreed price": 287.5
      },
      {
        "PRESCRIPTION NAME": "CANDESARTAN 8MG PER TAB",
        "Agreed price": 287.5
      },
      {
        "PRESCRIPTION NAME": "AFRABVITE DROPS (PER BOT)",
        "Agreed price": 292.5
      },
      {
        "PRESCRIPTION NAME": "NOSPAMIN DROPS",
        "Agreed price": 292.5
      },
      {
        "PRESCRIPTION NAME": "LIPITOR 10MG (per tab)",
        "Agreed price": 293.75
      },
      {
        "PRESCRIPTION NAME": "ZESTORETIC (per tab)",
        "Agreed price": 293.75
      },
      {
        "PRESCRIPTION NAME": "AMOXYL+CLAVULANIC ACID 1GM TAB (PER TAB)",
        "Agreed price": 300
      },
      {
        "PRESCRIPTION NAME": "BENYLIN EXPECTORANT 100MLS (per bot)",
        "Agreed price": 300
      },
      {
        "PRESCRIPTION NAME": "CALCIUM GLUCONATE INJ (per amp)",
        "Agreed price": 300
      },
      {
        "PRESCRIPTION NAME": "CELEBREX  200MG (per cap)",
        "Agreed price": 300
      },
      {
        "PRESCRIPTION NAME": "COLIPAN ALIXIR 5MG/5ML-100ML (per bot)",
        "Agreed price": 300
      },
      {
        "PRESCRIPTION NAME": "ANNUSOL SUPPOSITORIES (per supp)",
        "Agreed price": 312.5
      },
      {
        "PRESCRIPTION NAME": "BONJELA GEL 10G (per tube)",
        "Agreed price": 312.5
      },
      {
        "PRESCRIPTION NAME": "CLOTRIMAZOLE OVULE 100MG (per ovule)",
        "Agreed price": 312.5
      },
      {
        "PRESCRIPTION NAME": "Danazole Caps 200mg (per cap)",
        "Agreed price": 312.5
      },
      {
        "PRESCRIPTION NAME": "Galvus 50MG",
        "Agreed price": 312.5
      },
      {
        "PRESCRIPTION NAME": "PROMETHAZINE 5MG/5MG ELIXIR (per bot)",
        "Agreed price": 312.5
      },
      {
        "PRESCRIPTION NAME": "Tetanus Toxoid / ATS Each",
        "Agreed price": 312.5
      },
      {
        "PRESCRIPTION NAME": "ALBENDAZOLE SUSP 400MG/20ML (per bot)",
        "Agreed price": 325
      },
      {
        "PRESCRIPTION NAME": "BROMHEXINE SYRUP",
        "Agreed price": 325
      },
      {
        "PRESCRIPTION NAME": "CICATRIN POWDER (per bot)",
        "Agreed price": 325
      },
      {
        "PRESCRIPTION NAME": "LINCOMYCIN INJ 300MG (PER AMP)",
        "Agreed price": 325
      },
      {
        "PRESCRIPTION NAME": "Halothane injection",
        "Agreed price": 337.5
      },
      {
        "PRESCRIPTION NAME": "Thiopentone Sodium",
        "Agreed price": 337.5
      },
      {
        "PRESCRIPTION NAME": "HALFAN 250MG (per tab)",
        "Agreed price": 356.25
      },
      {
        "PRESCRIPTION NAME": "NOSPA INJ (PER AMP)",
        "Agreed price": 357.5
      },
      {
        "PRESCRIPTION NAME": "Terbinafine Tabs 250mg (per tab)",
        "Agreed price": 362.5
      },
      {
        "PRESCRIPTION NAME": "POTASSIUM CHLORIDE 3MG INJ (AMP)",
        "Agreed price": 373.75
      },
      {
        "PRESCRIPTION NAME": "BRONCHOLYTE  4MG/5ML ELIXIR (per bot)",
        "Agreed price": 375
      },
      {
        "PRESCRIPTION NAME": "CANDESARTAN 16MG PER TAB",
        "Agreed price": 375
      },
      {
        "PRESCRIPTION NAME": "EUCADIC 12.5MG  (per tab)",
        "Agreed price": 375
      },
      {
        "PRESCRIPTION NAME": "CEFUROXIME 250MG TAB",
        "Agreed price": 380
      },
      {
        "PRESCRIPTION NAME": "PROSCAR 5MG (per tab)",
        "Agreed price": 387.5
      },
      {
        "PRESCRIPTION NAME": "AZITHROMYCIN 500mg (per cap)",
        "Agreed price": 400
      },
      {
        "PRESCRIPTION NAME": "CYTOTEC (MISOPROSTOL) 200MCG (PER TAB)",
        "Agreed price": 400
      },
      {
        "PRESCRIPTION NAME": "PARACETAMOL SYRUP 125MG/5MLS (per bot)",
        "Agreed price": 400
      },
      {
        "PRESCRIPTION NAME": "PENICILLIN OINTMENT (PER TUBE)",
        "Agreed price": 400
      },
      {
        "PRESCRIPTION NAME": "VIT B COMPLEX SYRUP (per bot)",
        "Agreed price": 400
      },
      {
        "PRESCRIPTION NAME": "FUNBACT CREAM",
        "Agreed price": 406.25
      },
      {
        "PRESCRIPTION NAME": "MIST POTASSIUM CITRATE (per bot)",
        "Agreed price": 406.25
      },
      {
        "PRESCRIPTION NAME": "MODECATE 25MG INJ (per amp)",
        "Agreed price": 406.25
      },
      {
        "PRESCRIPTION NAME": "NYSTATIN (PER TAB)",
        "Agreed price": 406.25
      },
      {
        "PRESCRIPTION NAME": "PARALDEHYDE INJ",
        "Agreed price": 406.25
      },
      {
        "PRESCRIPTION NAME": "SABRESTEN CREAM DERMAL (per tube)",
        "Agreed price": 406.25
      },
      {
        "PRESCRIPTION NAME": "SODIUM BICARBONATE",
        "Agreed price": 406.25
      },
      {
        "PRESCRIPTION NAME": "CIPROTAB inj (Per Vial)",
        "Agreed price": 437.5
      },
      {
        "PRESCRIPTION NAME": "BENZYL PEROXIDE 10 LOTION (per tube)",
        "Agreed price": 462.5
      },
      {
        "PRESCRIPTION NAME": "BIOCOTEN CREAM 20G (per tube)",
        "Agreed price": 462.5
      },
      {
        "PRESCRIPTION NAME": "DILOXANIDE FUROATE 500MG (per tab)",
        "Agreed price": 475
      },
      {
        "PRESCRIPTION NAME": "XYLOCAINE INJ",
        "Agreed price": 481.25
      },
      {
        "PRESCRIPTION NAME": "ACCOLATE 20MG (per tab)",
        "Agreed price": 487.5
      },
      {
        "PRESCRIPTION NAME": "ARTESUNATE (per pack)",
        "Agreed price": 487.5
      },
      {
        "PRESCRIPTION NAME": "BETNESOL EYE OINTMENT",
        "Agreed price": 487.5
      },
      {
        "PRESCRIPTION NAME": "BETROSIL CREAM (per tube)",
        "Agreed price": 487.5
      },
      {
        "PRESCRIPTION NAME": "CANDIBIOTIC EAR DROPS",
        "Agreed price": 487.5
      },
      {
        "PRESCRIPTION NAME": "CYCLOGEST 400MG PESSARY (per pess)",
        "Agreed price": 487.5
      },
      {
        "PRESCRIPTION NAME": "FANSIDAR SUSP 525MG/5ML (per bot)",
        "Agreed price": 487.5
      },
      {
        "PRESCRIPTION NAME": "FUNGISOL POWDER 20MG (per bot)",
        "Agreed price": 487.5
      },
      {
        "PRESCRIPTION NAME": "GESTID 100ML (per bot)",
        "Agreed price": 487.5
      },
      {
        "PRESCRIPTION NAME": "LIPITOR 20MG (per tab)",
        "Agreed price": 487.5
      },
      {
        "PRESCRIPTION NAME": "OTOMED EAR DROP (per bot)",
        "Agreed price": 487.5
      },
      {
        "PRESCRIPTION NAME": "AMINOPHYLLINE INJ 25MG/ML (PER AMP)",
        "Agreed price": 500
      },
      {
        "PRESCRIPTION NAME": "AMOXYCILLIN  125MG/5ML-100MLS (per bot)",
        "Agreed price": 500
      },
      {
        "PRESCRIPTION NAME": "AMOXYL 500MG INJ/AMP",
        "Agreed price": 500
      },
      {
        "PRESCRIPTION NAME": "AMPICLOX 500MG INJ (per vial)",
        "Agreed price": 500
      },
      {
        "PRESCRIPTION NAME": "BENZYL BENZOATE OINTMENT (per bot)",
        "Agreed price": 500
      },
      {
        "PRESCRIPTION NAME": "BEOPTIC EAR DROP (per bot)",
        "Agreed price": 500
      },
      {
        "PRESCRIPTION NAME": "CHLORPROMAZINE 50MG INJ (per amp)",
        "Agreed price": 500
      },
      {
        "PRESCRIPTION NAME": "ERGOMETRINE INJ 1.5MG",
        "Agreed price": 500
      },
      {
        "PRESCRIPTION NAME": "FOLEY'S CATHETER (per piece)",
        "Agreed price": 500
      },
      {
        "PRESCRIPTION NAME": "GENTAMYCIN EYE/EAR DROP (per bot)",
        "Agreed price": 500
      },
      {
        "PRESCRIPTION NAME": "GYNODAKTARIN 400MG (per ovule)",
        "Agreed price": 500
      },
      {
        "PRESCRIPTION NAME": "HYDROCORTISONE 100MG INJ (per amp)",
        "Agreed price": 500
      },
      {
        "PRESCRIPTION NAME": "METRONIDAZOLE 200MG/5ML  (per bot)",
        "Agreed price": 500
      },
      {
        "PRESCRIPTION NAME": "METRONIDAZOLE INFUSION (per inf)",
        "Agreed price": 500
      },
      {
        "PRESCRIPTION NAME": "PREDNISOLONE EYE DROP (PER BOT).",
        "Agreed price": 500
      },
      {
        "PRESCRIPTION NAME": "TETANUS TOXOID  (per dose)",
        "Agreed price": 500
      },
      {
        "PRESCRIPTION NAME": "TRAMADOL 50MG INJ. (per vial)",
        "Agreed price": 500
      },
      {
        "PRESCRIPTION NAME": "VIT C SYRUP (per bot)",
        "Agreed price": 500
      },
      {
        "PRESCRIPTION NAME": "Tetanus Toxoid/ATS Each",
        "Agreed price": 500
      },
      {
        "PRESCRIPTION NAME": "NEXIUM TABS (per tab)",
        "Agreed price": 550
      },
      {
        "PRESCRIPTION NAME": "SINUFED SYRUP (per bot)",
        "Agreed price": 560
      },
      {
        "PRESCRIPTION NAME": "Lantanoprost",
        "Agreed price": 562.5
      },
      {
        "PRESCRIPTION NAME": "Retinol (Vit A) Syrup (per 200mls bot)",
        "Agreed price": 562.5
      },
      {
        "PRESCRIPTION NAME": "PARAFIN LIQUID (per bot)",
        "Agreed price": 568.75
      },
      {
        "PRESCRIPTION NAME": "AMPICLOX 250MG/5ML-100ML (per bot)",
        "Agreed price": 600
      },
      {
        "PRESCRIPTION NAME": "ARTEMETER 80MG INJ (PER AMP)",
        "Agreed price": 600
      },
      {
        "PRESCRIPTION NAME": "COMBANTRIN 250MG/5ML (per bot)",
        "Agreed price": 600
      },
      {
        "PRESCRIPTION NAME": "DICLOFENAC INJ  75MG (per amp)",
        "Agreed price": 600
      },
      {
        "PRESCRIPTION NAME": "GENTAMYCIN CREAM 15G (per tube)",
        "Agreed price": 600
      },
      {
        "PRESCRIPTION NAME": "IBUPROFEN 100MG/5ML (per bot)",
        "Agreed price": 600
      },
      {
        "PRESCRIPTION NAME": "Ketamin Inj (per vial)",
        "Agreed price": 600
      },
      {
        "PRESCRIPTION NAME": "PENTAZOCINE 30MG INJ (per amp)",
        "Agreed price": 600
      },
      {
        "PRESCRIPTION NAME": "RANFERON BLOOD TONIC 200MLS (per bot)",
        "Agreed price": 600
      },
      {
        "PRESCRIPTION NAME": "VIT K INJ (PER AMP)",
        "Agreed price": 600
      },
      {
        "PRESCRIPTION NAME": "ARTEMETHER SUSUPENSION (PER BOT)",
        "Agreed price": 625
      },
      {
        "PRESCRIPTION NAME": "OROFER SYRUP",
        "Agreed price": 625
      },
      {
        "PRESCRIPTION NAME": "POLYCROL FORTE GEL 100MLS (per bot)",
        "Agreed price": 625
      },
      {
        "PRESCRIPTION NAME": "POTASSIUM PERMANGANATE",
        "Agreed price": 625
      },
      {
        "PRESCRIPTION NAME": "VICRYL(PER STOOL)",
        "Agreed price": 625
      },
      {
        "PRESCRIPTION NAME": "Red Cell Count",
        "Agreed price": 625
      },
      {
        "PRESCRIPTION NAME": "BENYLIN WITH CODEINE (per bot)",
        "Agreed price": 650
      },
      {
        "PRESCRIPTION NAME": "CAMOSUNATE SUSP",
        "Agreed price": 650
      },
      {
        "PRESCRIPTION NAME": "CEPHALEXIN 125MG SYR",
        "Agreed price": 650
      },
      {
        "PRESCRIPTION NAME": "HYPOMELLOSE EYE DROP (per bot)",
        "Agreed price": 650
      },
      {
        "PRESCRIPTION NAME": "PHENOBARBITONE SYRUP (PER BOT)",
        "Agreed price": 650
      },
      {
        "PRESCRIPTION NAME": "PIRITON EXPECTORANT 100MLS (per bot)",
        "Agreed price": 650
      },
      {
        "PRESCRIPTION NAME": "PYRAZINAMIDE SYRUP (per bot)",
        "Agreed price": 650
      },
      {
        "PRESCRIPTION NAME": "SABRESTEN VAG CREAM (per tube)",
        "Agreed price": 650
      },
      {
        "PRESCRIPTION NAME": "DICYNONE 250MG (per amp)",
        "Agreed price": 687.5
      },
      {
        "PRESCRIPTION NAME": "ADRENALIN INJ 1MG (per amp)",
        "Agreed price": 700
      },
      {
        "PRESCRIPTION NAME": "CHLORPHENIRAMINE 2MG/5ML (per bot)",
        "Agreed price": 700
      },
      {
        "PRESCRIPTION NAME": "LAMIVUDINE 100MG (per tab)",
        "Agreed price": 700
      },
      {
        "PRESCRIPTION NAME": "CASTOR OIL (PER BOT)",
        "Agreed price": 731.25
      },
      {
        "PRESCRIPTION NAME": "MENTHODEX  (per bot)",
        "Agreed price": 731.25
      },
      {
        "PRESCRIPTION NAME": "NYSTATIN CREAM (PER TUBE)",
        "Agreed price": 731.25
      },
      {
        "PRESCRIPTION NAME": "SALBUTAMOL SYRUP (PER BOT)",
        "Agreed price": 731.25
      },
      {
        "PRESCRIPTION NAME": "CAMOSUNATE TAB (PER PACK)",
        "Agreed price": 747.5
      },
      {
        "PRESCRIPTION NAME": "HYDROCORTISONE 15MG (per tube)",
        "Agreed price": 750
      },
      {
        "PRESCRIPTION NAME": "IVYZINC",
        "Agreed price": 750
      },
      {
        "PRESCRIPTION NAME": "MIST MAG. (PER BOT).",
        "Agreed price": 750
      },
      {
        "PRESCRIPTION NAME": "NEUROGESIC GEL (per tube)",
        "Agreed price": 750
      },
      {
        "PRESCRIPTION NAME": "KENACOMB CREAM (per tube)",
        "Agreed price": 780
      },
      {
        "PRESCRIPTION NAME": "SALICYLIC ACID OINT 20% (per bot)",
        "Agreed price": 781.25
      },
      {
        "PRESCRIPTION NAME": "NPI Immunisation - Each (Unregistered Enrollees)",
        "Agreed price": 781.25
      },
      {
        "PRESCRIPTION NAME": "AMIKACIN INJ",
        "Agreed price": 800
      },
      {
        "PRESCRIPTION NAME": "APRESOLINE 20MG INJ (per amp)",
        "Agreed price": 800
      },
      {
        "PRESCRIPTION NAME": "TRANXEMIC ACID 100MG INJ (PER AMP)",
        "Agreed price": 800
      },
      {
        "PRESCRIPTION NAME": "Fasting Blood Sugar/Random Blood Sugar Each",
        "Agreed price": 800
      },
      {
        "PRESCRIPTION NAME": "Urinalysis",
        "Agreed price": 800
      },
      {
        "PRESCRIPTION NAME": "Urine Pregnancy Test",
        "Agreed price": 800
      },
      {
        "PRESCRIPTION NAME": "Malaria Parasite",
        "Agreed price": 800
      },
      {
        "PRESCRIPTION NAME": "PCV/Haemoglobin",
        "Agreed price": 800
      },
      {
        "PRESCRIPTION NAME": "MCV/MCH/MCHC Each",
        "Agreed price": 800
      },
      {
        "PRESCRIPTION NAME": "ALAXIN SUSP 10MG/5ML-80ML (per bot)",
        "Agreed price": 812.5
      },
      {
        "PRESCRIPTION NAME": "EUCALYPTUS OIL (per bot)",
        "Agreed price": 812.5
      },
      {
        "PRESCRIPTION NAME": "UNASYN INJECTION (PER AMP)",
        "Agreed price": 812.5
      },
      {
        "PRESCRIPTION NAME": "MIXTARD INSULIN PER  40 I.U/ ML",
        "Agreed price": 845
      },
      {
        "PRESCRIPTION NAME": "GESTID 200ML (per bot)",
        "Agreed price": 850
      },
      {
        "PRESCRIPTION NAME": "MANNITOL INFUSION 10%",
        "Agreed price": 850
      },
      {
        "PRESCRIPTION NAME": "ONDANSETRONE INJ (PER AMP)",
        "Agreed price": 850
      },
      {
        "PRESCRIPTION NAME": "DEPO PROVERA INJ (per vial)",
        "Agreed price": 875
      },
      {
        "PRESCRIPTION NAME": "Optodexin",
        "Agreed price": 875
      },
      {
        "PRESCRIPTION NAME": "FANSIDAR INJ 525MG (per amp)",
        "Agreed price": 881.25
      },
      {
        "PRESCRIPTION NAME": "APPATIM EYE DROP",
        "Agreed price": 893.75
      },
      {
        "PRESCRIPTION NAME": "CEPHALEXIN 250MG SYR",
        "Agreed price": 893.75
      },
      {
        "PRESCRIPTION NAME": "INTERFLOX 500MG (per cap)",
        "Agreed price": 893.75
      },
      {
        "PRESCRIPTION NAME": "OMEPRAZOLE  40MG INJ (PER AMP)",
        "Agreed price": 893.75
      },
      {
        "PRESCRIPTION NAME": "SPERSALLERGE EYE DROP (per bot)",
        "Agreed price": 893.75
      },
      {
        "PRESCRIPTION NAME": "TIMOLOL EYE DROP 0.5% (per bot)",
        "Agreed price": 893.75
      },
      {
        "PRESCRIPTION NAME": "ERYTHROMYCIN 125MG/5ML (per bot)",
        "Agreed price": 900
      },
      {
        "PRESCRIPTION NAME": "NORMAL SALINE",
        "Agreed price": 900
      },
      {
        "PRESCRIPTION NAME": "QUININE SYRUP 200MLS (per bot)",
        "Agreed price": 900
      },
      {
        "PRESCRIPTION NAME": "Gamma Glutamyl Transferace",
        "Agreed price": 937.5
      },
      {
        "PRESCRIPTION NAME": "CPK",
        "Agreed price": 937.5
      },
      {
        "PRESCRIPTION NAME": "LDH",
        "Agreed price": 937.5
      },
      {
        "PRESCRIPTION NAME": "Amylase",
        "Agreed price": 937.5
      },
      {
        "PRESCRIPTION NAME": "Creatine Kinase",
        "Agreed price": 937.5
      },
      {
        "PRESCRIPTION NAME": "CIPROFLOXACIN 200MG INFUSION (per bot)",
        "Agreed price": 950
      },
      {
        "PRESCRIPTION NAME": "SKINHEAL CREAM (PER TUBE)",
        "Agreed price": 950
      },
      {
        "PRESCRIPTION NAME": "BRONCHICUM (per bot)",
        "Agreed price": 975
      },
      {
        "PRESCRIPTION NAME": "CAMOQUINE 50MG/5ML-60ML (per bot)",
        "Agreed price": 975
      },
      {
        "PRESCRIPTION NAME": "DAKTACORT PESSARIES (PACK)",
        "Agreed price": 975
      },
      {
        "PRESCRIPTION NAME": "HYCOMYCIN EYEDROP (per bot)",
        "Agreed price": 975
      },
      {
        "PRESCRIPTION NAME": "IVYDEXGENT (PER BOT)",
        "Agreed price": 975
      },
      {
        "PRESCRIPTION NAME": "IVYMORCELL EYE DROP",
        "Agreed price": 975
      },
      {
        "PRESCRIPTION NAME": "LORATIDINE SYRUP",
        "Agreed price": 975
      },
      {
        "PRESCRIPTION NAME": "MELROSUM WITH CODEIN 100ML (per bot)",
        "Agreed price": 975
      },
      {
        "PRESCRIPTION NAME": "MILK OF MAGNESIA(100MLS)",
        "Agreed price": 975
      },
      {
        "PRESCRIPTION NAME": "OLFEN GEL (per tube)",
        "Agreed price": 975
      },
      {
        "PRESCRIPTION NAME": "PHENEGAN CREAM 2% 30G (per tube)",
        "Agreed price": 975
      },
      {
        "PRESCRIPTION NAME": "PILOCARPINE EYE DROP 2% (per bot)",
        "Agreed price": 975
      },
      {
        "PRESCRIPTION NAME": "SODIUM CHROMOGLYCATE EYE DROP (per bot)",
        "Agreed price": 975
      },
      {
        "PRESCRIPTION NAME": "ARTESUNATE SYR (PER BOT)",
        "Agreed price": 1000
      },
      {
        "PRESCRIPTION NAME": "BENZYL PEROXIDE  5 LOTION (per tube)",
        "Agreed price": 1000
      },
      {
        "PRESCRIPTION NAME": "DARROWS SOLUTION 1/2 strength (per inf)",
        "Agreed price": 1000
      },
      {
        "PRESCRIPTION NAME": "DARROWS SOLUTION FULL strength (per inf)",
        "Agreed price": 1000
      },
      {
        "PRESCRIPTION NAME": "DEXTROSE 10% INFUSION",
        "Agreed price": 1000
      },
      {
        "PRESCRIPTION NAME": "DEXTROSE 4.3% / NORMAL SALINE (per inf)",
        "Agreed price": 1000
      },
      {
        "PRESCRIPTION NAME": "DEXTROSE 5% (per inf)",
        "Agreed price": 1000
      },
      {
        "PRESCRIPTION NAME": "DEXTROSE 50% (per inf)",
        "Agreed price": 1000
      },
      {
        "PRESCRIPTION NAME": "DEXTROSE SALINE 5%",
        "Agreed price": 1000
      },
      {
        "PRESCRIPTION NAME": "DIAZEPAM 10MG (per amp)",
        "Agreed price": 1000
      },
      {
        "PRESCRIPTION NAME": "NYSTATIN ORAL DROPS 30MLS (per bot)",
        "Agreed price": 1000
      },
      {
        "PRESCRIPTION NAME": "OTRIVIN NASAL DROPS 0.05% 10MLS (per bot)",
        "Agreed price": 1000
      },
      {
        "PRESCRIPTION NAME": "Paracetamol infusion",
        "Agreed price": 1000
      },
      {
        "PRESCRIPTION NAME": "RANITHIDINE INJ 50MG (PER AMP)",
        "Agreed price": 1000
      },
      {
        "PRESCRIPTION NAME": "RINGERS LACTATE INJ",
        "Agreed price": 1000
      },
      {
        "PRESCRIPTION NAME": "Minor Wound Dressing/Day (Out Of Station Emergencies)",
        "Agreed price": 1000
      },
      {
        "PRESCRIPTION NAME": "Widal",
        "Agreed price": 1000
      },
      {
        "PRESCRIPTION NAME": "Blood Grouping",
        "Agreed price": 1000
      },
      {
        "PRESCRIPTION NAME": "WBC (Total)",
        "Agreed price": 1000
      },
      {
        "PRESCRIPTION NAME": "WBC ( Differential)",
        "Agreed price": 1000
      },
      {
        "PRESCRIPTION NAME": "Platelet Count",
        "Agreed price": 1000
      },
      {
        "PRESCRIPTION NAME": "Reticulocyte Count",
        "Agreed price": 1000
      },
      {
        "PRESCRIPTION NAME": "Peripheral Blood Film",
        "Agreed price": 1000
      },
      {
        "PRESCRIPTION NAME": "Hb Genotype",
        "Agreed price": 1000
      },
      {
        "PRESCRIPTION NAME": "ANTISIN-PRIVIN EYE DROP-10ML (per bot)",
        "Agreed price": 1056.25
      },
      {
        "PRESCRIPTION NAME": "GYNOTROSID 100MG (per ovule)",
        "Agreed price": 1056.25
      },
      {
        "PRESCRIPTION NAME": "PILOCARPINE EYE DROP 4% (per bot)",
        "Agreed price": 1056.25
      },
      {
        "PRESCRIPTION NAME": "VISINE EYE DROP (per bot)",
        "Agreed price": 1056.25
      },
      {
        "PRESCRIPTION NAME": "FLOXAPEN 125MG/5ML (per bot)",
        "Agreed price": 1062.5
      },
      {
        "PRESCRIPTION NAME": "OTRIVIN NASAL DROP 0.1% 10MLS (per bot)",
        "Agreed price": 1062.5
      },
      {
        "PRESCRIPTION NAME": "BEOPTIC EYE (per bot)",
        "Agreed price": 1125
      },
      {
        "PRESCRIPTION NAME": "GESTONE 50MG (per amp)",
        "Agreed price": 1125
      },
      {
        "PRESCRIPTION NAME": "Salbutamol Aerosol (per spray can)",
        "Agreed price": 1125
      },
      {
        "PRESCRIPTION NAME": "CROMAX 4 EYE DROP",
        "Agreed price": 1137.5
      },
      {
        "PRESCRIPTION NAME": "SALINE NASAL DROP (per tab)",
        "Agreed price": 1137.5
      },
      {
        "PRESCRIPTION NAME": "STARXON (per vial)",
        "Agreed price": 1137.5
      },
      {
        "PRESCRIPTION NAME": "SUFFRATULE(PER PACK)",
        "Agreed price": 1137.5
      },
      {
        "PRESCRIPTION NAME": "CEFIXIME SYR (PER BOT)",
        "Agreed price": 1187.5
      },
      {
        "PRESCRIPTION NAME": "Terbinafine CREAM 15G (per tube)",
        "Agreed price": 1193.75
      },
      {
        "PRESCRIPTION NAME": "CIPROFLOXACIN EYE DROP",
        "Agreed price": 1200
      },
      {
        "PRESCRIPTION NAME": "CLOTRIMAZOLE CREAM 20G (per tube)",
        "Agreed price": 1200
      },
      {
        "PRESCRIPTION NAME": "Sodium/Chloride/Potassium/Bicarbonate Each",
        "Agreed price": 1200
      },
      {
        "PRESCRIPTION NAME": "Pregnancy Test - HCG (Blood)",
        "Agreed price": 1200
      },
      {
        "PRESCRIPTION NAME": "DEPOMEDROL 40MG (per vial)",
        "Agreed price": 1218.75
      },
      {
        "PRESCRIPTION NAME": "ACTIFIED SYRUP",
        "Agreed price": 1250
      },
      {
        "PRESCRIPTION NAME": "BIVACYN  SPRAY (per pack)",
        "Agreed price": 1250
      },
      {
        "PRESCRIPTION NAME": "DETRUSITOL XL 4MG (per cap)",
        "Agreed price": 1250
      },
      {
        "PRESCRIPTION NAME": "ENCEPHABOL SYR 100MLS (per bot)",
        "Agreed price": 1250
      },
      {
        "PRESCRIPTION NAME": "Fluocinolone cream",
        "Agreed price": 1250
      },
      {
        "PRESCRIPTION NAME": "IVYCROM EYE DROP",
        "Agreed price": 1250
      },
      {
        "PRESCRIPTION NAME": "IVYFLUR",
        "Agreed price": 1250
      },
      {
        "PRESCRIPTION NAME": "KETOLAC INJ",
        "Agreed price": 1250
      },
      {
        "PRESCRIPTION NAME": "Urea Clearance",
        "Agreed price": 1250
      },
      {
        "PRESCRIPTION NAME": "ARTEMETHER/LUMEFANTRINE SUSPENSION PER BOTTLE",
        "Agreed price": 1300
      },
      {
        "PRESCRIPTION NAME": "CETRIZINE SYRUP",
        "Agreed price": 1300
      },
      {
        "PRESCRIPTION NAME": "FEROGLOBIN 200ML (per bot)",
        "Agreed price": 1300
      },
      {
        "PRESCRIPTION NAME": "MAXIDEX EYE DROP (per bot)",
        "Agreed price": 1300
      },
      {
        "PRESCRIPTION NAME": "MYDRIACYL EYE DROP (per bot)",
        "Agreed price": 1300
      },
      {
        "PRESCRIPTION NAME": "SGOT/SGPT Each",
        "Agreed price": 1300
      },
      {
        "PRESCRIPTION NAME": "Alkaline Prosphatase",
        "Agreed price": 1300
      },
      {
        "PRESCRIPTION NAME": "CLOBETASOL 45G CREAM (per tube)",
        "Agreed price": 1375
      },
      {
        "PRESCRIPTION NAME": "GESTONE 100MG (per amp)",
        "Agreed price": 1375
      },
      {
        "PRESCRIPTION NAME": "NEPAFLAM EYE DROP",
        "Agreed price": 1375
      },
      {
        "PRESCRIPTION NAME": "BETAMETHASONE SODIUM EYE DROP",
        "Agreed price": 1381.25
      },
      {
        "PRESCRIPTION NAME": "DERMOVATE CREAM 25G (per tube)",
        "Agreed price": 1381.25
      },
      {
        "PRESCRIPTION NAME": "FLUCONAZOLE SYR",
        "Agreed price": 1397.5
      },
      {
        "PRESCRIPTION NAME": "ARTEMETHER/LUMEFANTRINE 80/480 (PER PACK)",
        "Agreed price": 1400
      },
      {
        "PRESCRIPTION NAME": "AMPICLOX DROPS",
        "Agreed price": 1462.5
      },
      {
        "PRESCRIPTION NAME": "ANTHISAN CREAM 25MG (per tube)",
        "Agreed price": 1462.5
      },
      {
        "PRESCRIPTION NAME": "NYOLOL 0.5 EYE DROP (per bot)",
        "Agreed price": 1462.5
      },
      {
        "PRESCRIPTION NAME": "PRIMOLUT DEPOT 250MG (per vial)",
        "Agreed price": 1462.5
      },
      {
        "PRESCRIPTION NAME": "TEAR NATURALE EYE DROP (per bot)",
        "Agreed price": 1462.5
      },
      {
        "PRESCRIPTION NAME": "AMOXYL+CLAVULANIC ACID 1.2G (PER AMP)",
        "Agreed price": 1500
      },
      {
        "PRESCRIPTION NAME": "BETNESOL EYE/ EAR/ NOSE DROP (per bot)",
        "Agreed price": 1500
      },
      {
        "PRESCRIPTION NAME": "DERMAZINE CREAM  50MG (per tube)",
        "Agreed price": 1500
      },
      {
        "PRESCRIPTION NAME": "EURAX CREAM (per tube)",
        "Agreed price": 1500
      },
      {
        "PRESCRIPTION NAME": "GATE DPX EYE DROP",
        "Agreed price": 1500
      },
      {
        "PRESCRIPTION NAME": "GYNOTROSID 300MG (per ovule)",
        "Agreed price": 1500
      },
      {
        "PRESCRIPTION NAME": "LEVOFLOXACIN INF 100ML",
        "Agreed price": 1500
      },
      {
        "PRESCRIPTION NAME": "PENTAVALENT VACCINE",
        "Agreed price": 1500
      },
      {
        "PRESCRIPTION NAME": "Major Wound Dressing/Day",
        "Agreed price": 1500
      },
      {
        "PRESCRIPTION NAME": "Microscopy Stool/Urine Each",
        "Agreed price": 1500
      },
      {
        "PRESCRIPTION NAME": "VDRL",
        "Agreed price": 1500
      },
      {
        "PRESCRIPTION NAME": "Hepatitis B Surface Antigen Screening (HbsAg)",
        "Agreed price": 1500
      },
      {
        "PRESCRIPTION NAME": "ESR Westergren",
        "Agreed price": 1500
      },
      {
        "PRESCRIPTION NAME": "DEPIXOL 20MG (per amp)",
        "Agreed price": 1543.75
      },
      {
        "PRESCRIPTION NAME": "HALFAN 100MG/5ML (per bot)",
        "Agreed price": 1543.75
      },
      {
        "PRESCRIPTION NAME": "LOCASALENE CREAM 30MG (per tube)",
        "Agreed price": 1543.75
      },
      {
        "PRESCRIPTION NAME": "MAXITROL EYE DROP (per bot)",
        "Agreed price": 1543.75
      },
      {
        "PRESCRIPTION NAME": "NYOLOL OPTHALMIC GEL 0.1% 5G (per bot)",
        "Agreed price": 1543.75
      },
      {
        "PRESCRIPTION NAME": "TOBRAMYCIN OINTMENT",
        "Agreed price": 1543.75
      },
      {
        "PRESCRIPTION NAME": "TOBREX  EYE DROP",
        "Agreed price": 1543.75
      },
      {
        "PRESCRIPTION NAME": "TRAVOCORT CREAM (per tab)",
        "Agreed price": 1543.75
      },
      {
        "PRESCRIPTION NAME": "RHINATHIOL SYRUP (per 100ml bot)",
        "Agreed price": 1600
      },
      {
        "PRESCRIPTION NAME": "OKACIN EYE DROP (per bot)",
        "Agreed price": 1625
      },
      {
        "PRESCRIPTION NAME": "NIZORAL CREAM 15MG (per tube)",
        "Agreed price": 1700
      },
      {
        "PRESCRIPTION NAME": "ALOMIDE EYEDROP 10MLS (per bot)",
        "Agreed price": 1787.5
      },
      {
        "PRESCRIPTION NAME": "CILOXAN EYE DROP (per bot)",
        "Agreed price": 1787.5
      },
      {
        "PRESCRIPTION NAME": "HYPOTEARS GEL",
        "Agreed price": 1787.5
      },
      {
        "PRESCRIPTION NAME": "IKACLOMIN 50MG (per tab)",
        "Agreed price": 1787.5
      },
      {
        "PRESCRIPTION NAME": "TROSYD CREAM (per tube)",
        "Agreed price": 1787.5
      },
      {
        "PRESCRIPTION NAME": "ACICLOVIR CREAM 10MG (per tube)",
        "Agreed price": 1800
      },
      {
        "PRESCRIPTION NAME": "AMOXYL+CLAVULANIC ACID 312.5MG SUSP (PER BOT).",
        "Agreed price": 1800
      },
      {
        "PRESCRIPTION NAME": "AMOXYL+CLAVULANIC ACID 228MG SUSP (PER BOT).",
        "Agreed price": 1800
      },
      {
        "PRESCRIPTION NAME": "Beclomethasone Aerosol Inhalation (per can)",
        "Agreed price": 1875
      },
      {
        "PRESCRIPTION NAME": "FOLIC ACID 5MG (per tab)",
        "Agreed price": 1875
      },
      {
        "PRESCRIPTION NAME": "ADVANTAN OINTMENT (per tube)",
        "Agreed price": 1950
      },
      {
        "PRESCRIPTION NAME": "MILK OF MAGNESIA  PHILIP 200MLS (per bot)",
        "Agreed price": 1950
      },
      {
        "PRESCRIPTION NAME": "NIZORAL SHAMPOO (per bot)",
        "Agreed price": 1950
      },
      {
        "PRESCRIPTION NAME": "SALBUTAMOL 100MCG INHALER (per piece)",
        "Agreed price": 2000
      },
      {
        "PRESCRIPTION NAME": "Registration",
        "Agreed price": 2000
      },
      {
        "PRESCRIPTION NAME": "Nursing Care Per Diem",
        "Agreed price": 2000
      },
      {
        "PRESCRIPTION NAME": "Urea/Creatinine Each",
        "Agreed price": 2000
      },
      {
        "PRESCRIPTION NAME": "Total Protein/Albumin Each",
        "Agreed price": 2000
      },
      {
        "PRESCRIPTION NAME": "G-6 Phosphate Dehydrogenase",
        "Agreed price": 2000
      },
      {
        "PRESCRIPTION NAME": "Cholesterol",
        "Agreed price": 2000
      },
      {
        "PRESCRIPTION NAME": "Tryglyceride",
        "Agreed price": 2000
      },
      {
        "PRESCRIPTION NAME": "LDL",
        "Agreed price": 2000
      },
      {
        "PRESCRIPTION NAME": "HDL",
        "Agreed price": 2000
      },
      {
        "PRESCRIPTION NAME": "Urine M/C/S",
        "Agreed price": 2000
      },
      {
        "PRESCRIPTION NAME": "Stool M/C/S",
        "Agreed price": 2000
      },
      {
        "PRESCRIPTION NAME": "HVS/Urethral Swab M/C/S Each",
        "Agreed price": 2000
      },
      {
        "PRESCRIPTION NAME": "Ear/Nose/Throat Swab M/C/S Each",
        "Agreed price": 2000
      },
      {
        "PRESCRIPTION NAME": "Sputum M/C/S",
        "Agreed price": 2000
      },
      {
        "PRESCRIPTION NAME": "Wound/Pus/Aspirate M/C/S Each",
        "Agreed price": 2000
      },
      {
        "PRESCRIPTION NAME": "Cross Matching",
        "Agreed price": 2000
      },
      {
        "PRESCRIPTION NAME": "INSULIN LENTEL 40 IU (per vial)",
        "Agreed price": 2018.75
      },
      {
        "PRESCRIPTION NAME": "FLIXONASE NASAL SPRAY",
        "Agreed price": 2193.75
      },
      {
        "PRESCRIPTION NAME": "VOLTAREN EYE DROP",
        "Agreed price": 2193.75
      },
      {
        "PRESCRIPTION NAME": "AZITHROMYCIN SUSPENSION PER BOTTLE",
        "Agreed price": 2200
      },
      {
        "PRESCRIPTION NAME": "CEFTAZIDINE 1G ING",
        "Agreed price": 2200
      },
      {
        "PRESCRIPTION NAME": "CEFUROXIME 750MG INJ",
        "Agreed price": 2200
      },
      {
        "PRESCRIPTION NAME": "Triamcinolone Inj (per amp)",
        "Agreed price": 2200
      },
      {
        "PRESCRIPTION NAME": "DEPROSALIC ACID OINTMENT (PER TUBE)",
        "Agreed price": 2275
      },
      {
        "PRESCRIPTION NAME": "ASO Titre",
        "Agreed price": 2343.75
      },
      {
        "PRESCRIPTION NAME": "BECONASENASAL DROP (per pack)",
        "Agreed price": 2375
      },
      {
        "PRESCRIPTION NAME": "RETIN A CREAM (per tube)",
        "Agreed price": 2437.5
      },
      {
        "PRESCRIPTION NAME": "CEFTRIAXONE 1G INJ /AMP",
        "Agreed price": 2500
      },
      {
        "PRESCRIPTION NAME": "ENCEPHABOL SYR 120MLS (per bot)",
        "Agreed price": 2500
      },
      {
        "PRESCRIPTION NAME": "ZADITEN EYE DROPS (per bot)",
        "Agreed price": 2500
      },
      {
        "PRESCRIPTION NAME": "General Consultation",
        "Agreed price": 2500
      },
      {
        "PRESCRIPTION NAME": "Routine Intravenous Infusion/500 mls + Materials",
        "Agreed price": 2500
      },
      {
        "PRESCRIPTION NAME": "Nebulisation (Subsequent)",
        "Agreed price": 2500
      },
      {
        "PRESCRIPTION NAME": "Total/Direct Bilirubin  Each",
        "Agreed price": 2500
      },
      {
        "PRESCRIPTION NAME": "Screening For HIV 1 & 2",
        "Agreed price": 2500
      },
      {
        "PRESCRIPTION NAME": "MOSEGOR 100MLS (per bot)",
        "Agreed price": 2550
      },
      {
        "PRESCRIPTION NAME": "CERUMOL EAR DROP (per bot)",
        "Agreed price": 2600
      },
      {
        "PRESCRIPTION NAME": "ERYTHROMYCIN CREAM 4% 30MG (per tube)",
        "Agreed price": 2875
      },
      {
        "PRESCRIPTION NAME": "ISOPLASMA",
        "Agreed price": 2875
      },
      {
        "PRESCRIPTION NAME": "DAKTACORT CREAM (PER TUBE)",
        "Agreed price": 3000
      },
      {
        "PRESCRIPTION NAME": "ENCEPHABOL SYR  200MLS (per bot)",
        "Agreed price": 3000
      },
      {
        "PRESCRIPTION NAME": "Feeding Per Diem (Private Ward)",
        "Agreed price": 3000
      },
      {
        "PRESCRIPTION NAME": "Feeding Per Diem (Semi-Private Ward)",
        "Agreed price": 3000
      },
      {
        "PRESCRIPTION NAME": "Feeding Per Diem (General Ward)",
        "Agreed price": 3000
      },
      {
        "PRESCRIPTION NAME": "Glucose Tolerance Test",
        "Agreed price": 3000
      },
      {
        "PRESCRIPTION NAME": "Stool Ocult Blood",
        "Agreed price": 3000
      },
      {
        "PRESCRIPTION NAME": "Full Blood Count",
        "Agreed price": 3000
      },
      {
        "PRESCRIPTION NAME": "PATANOL (OLOPATADINE) EYE DROP",
        "Agreed price": 3087.5
      },
      {
        "PRESCRIPTION NAME": "CLEXANE INJ",
        "Agreed price": 3125
      },
      {
        "PRESCRIPTION NAME": "Apical/Lordotic",
        "Agreed price": 3125
      },
      {
        "PRESCRIPTION NAME": "Sternum",
        "Agreed price": 3125
      },
      {
        "PRESCRIPTION NAME": "Pelvic",
        "Agreed price": 3125
      },
      {
        "PRESCRIPTION NAME": "Obstetric",
        "Agreed price": 3125
      },
      {
        "PRESCRIPTION NAME": "DEPOMEDROL 80MG (per vial)",
        "Agreed price": 3412.5
      },
      {
        "PRESCRIPTION NAME": "VANCOMYCIN 1G INJ (PER AMP)",
        "Agreed price": 3412.5
      },
      {
        "PRESCRIPTION NAME": "CHOTIGON 5000IU (per amp)",
        "Agreed price": 3575
      },
      {
        "PRESCRIPTION NAME": "PREGYNL 5000 IU (per pack)",
        "Agreed price": 3575
      },
      {
        "PRESCRIPTION NAME": "HAEMACCEL INFUSION. (per pint)",
        "Agreed price": 3750
      },
      {
        "PRESCRIPTION NAME": "Abdomen (Plain)",
        "Agreed price": 3750
      },
      {
        "PRESCRIPTION NAME": "KENALOG 40MG (per amp)",
        "Agreed price": 4000
      },
      {
        "PRESCRIPTION NAME": "PROSPENEM(PER VIAL)",
        "Agreed price": 4000
      },
      {
        "PRESCRIPTION NAME": "SOLUSET (per piece)",
        "Agreed price": 4000
      },
      {
        "PRESCRIPTION NAME": "Hepatitis B Vaccine/Dose",
        "Agreed price": 4000
      },
      {
        "PRESCRIPTION NAME": "Phototherapy Per Diem",
        "Agreed price": 4000
      },
      {
        "PRESCRIPTION NAME": "Total Acid Phosphatase/Prostatic Each",
        "Agreed price": 4000
      },
      {
        "PRESCRIPTION NAME": "Blood Culture & Sensitivity",
        "Agreed price": 4000
      },
      {
        "PRESCRIPTION NAME": "Direct/Indirect Coombs Test Each",
        "Agreed price": 4000
      },
      {
        "PRESCRIPTION NAME": "FLIXOTIDE ACCUHALER (per accu)",
        "Agreed price": 4375
      },
      {
        "PRESCRIPTION NAME": "Abdomen",
        "Agreed price": 4500
      },
      {
        "PRESCRIPTION NAME": "MONOTARD INSULIN HM 100 IU/ML (per vial)",
        "Agreed price": 4550
      },
      {
        "PRESCRIPTION NAME": "Haemophilus Influenzae Type B (HiB) Vaccine",
        "Agreed price": 4687.5
      },
      {
        "PRESCRIPTION NAME": "CEFUROXIME SYR",
        "Agreed price": 5000
      },
      {
        "PRESCRIPTION NAME": "General Ward Per Diem",
        "Agreed price": 5000
      },
      {
        "PRESCRIPTION NAME": "Suturing Of Simple Laceration",
        "Agreed price": 5000
      },
      {
        "PRESCRIPTION NAME": "Nebulisation (Initial)",
        "Agreed price": 5000
      },
      {
        "PRESCRIPTION NAME": "Incubator Care Per Diem",
        "Agreed price": 5000
      },
      {
        "PRESCRIPTION NAME": "Oxygen Therapy Per Diem",
        "Agreed price": 5000
      },
      {
        "PRESCRIPTION NAME": "Ear Piercing For Female Baby",
        "Agreed price": 5000
      },
      {
        "PRESCRIPTION NAME": "Tongue Tie Release",
        "Agreed price": 5000
      },
      {
        "PRESCRIPTION NAME": "Serum Electrolytes/Urea/Creatinine",
        "Agreed price": 5000
      },
      {
        "PRESCRIPTION NAME": "Creatine Clearance",
        "Agreed price": 5000
      },
      {
        "PRESCRIPTION NAME": "HIV Confirmatory",
        "Agreed price": 5000
      },
      {
        "PRESCRIPTION NAME": "Clavicle",
        "Agreed price": 5000
      },
      {
        "PRESCRIPTION NAME": "Chest (PA/AP)",
        "Agreed price": 5000
      },
      {
        "PRESCRIPTION NAME": "Cervical Spine (Obliques)",
        "Agreed price": 5000
      },
      {
        "PRESCRIPTION NAME": "Sacrum",
        "Agreed price": 5000
      },
      {
        "PRESCRIPTION NAME": "Sacro Iliac Joint (S.I.J.)",
        "Agreed price": 5000
      },
      {
        "PRESCRIPTION NAME": "Sacro-Coccxy",
        "Agreed price": 5000
      },
      {
        "PRESCRIPTION NAME": "Sella Turcica",
        "Agreed price": 5000
      },
      {
        "PRESCRIPTION NAME": "Tagential",
        "Agreed price": 5000
      },
      {
        "PRESCRIPTION NAME": "Occipito-Mental (Om)",
        "Agreed price": 5000
      },
      {
        "PRESCRIPTION NAME": "Post Nasal Space",
        "Agreed price": 5000
      },
      {
        "PRESCRIPTION NAME": "Internal Auditory Meatus",
        "Agreed price": 5000
      },
      {
        "PRESCRIPTION NAME": "Bladder",
        "Agreed price": 5000
      },
      {
        "PRESCRIPTION NAME": "ANTI RABIES VACCINE  (per vial)",
        "Agreed price": 5468.75
      },
      {
        "PRESCRIPTION NAME": "Measles, Mumps & Rubella (MMR) Vaccine",
        "Agreed price": 5468.75
      },
      {
        "PRESCRIPTION NAME": "Anti Rabies Vaccine",
        "Agreed price": 5468.75
      },
      {
        "PRESCRIPTION NAME": "Meningitis Vaccine",
        "Agreed price": 5468.75
      },
      {
        "PRESCRIPTION NAME": "Hand",
        "Agreed price": 5500
      },
      {
        "PRESCRIPTION NAME": "Wrist",
        "Agreed price": 5500
      },
      {
        "PRESCRIPTION NAME": "Forearm",
        "Agreed price": 5500
      },
      {
        "PRESCRIPTION NAME": "Elbow",
        "Agreed price": 5500
      },
      {
        "PRESCRIPTION NAME": "Humerus",
        "Agreed price": 5500
      },
      {
        "PRESCRIPTION NAME": "Foot/Toe",
        "Agreed price": 5500
      },
      {
        "PRESCRIPTION NAME": "Ankle",
        "Agreed price": 5500
      },
      {
        "PRESCRIPTION NAME": "Leg (Tibia/Fibula)",
        "Agreed price": 5500
      },
      {
        "PRESCRIPTION NAME": "Knee",
        "Agreed price": 5500
      },
      {
        "PRESCRIPTION NAME": "Thoracic Inlet",
        "Agreed price": 5500
      },
      {
        "PRESCRIPTION NAME": "Lateral Neck (Soft Tissue)",
        "Agreed price": 5500
      },
      {
        "PRESCRIPTION NAME": "ACTRAPID INSULIN 10MLS (per vial)",
        "Agreed price": 5625
      },
      {
        "PRESCRIPTION NAME": "MIXTARD INSULIN 3ML (per catridge)",
        "Agreed price": 5625
      },
      {
        "PRESCRIPTION NAME": "CEFPODOXIME(ORELOX) Susp.",
        "Agreed price": 6000
      },
      {
        "PRESCRIPTION NAME": "SERETIDE DISKUS - CHILDREN (per pack)",
        "Agreed price": 6000
      },
      {
        "PRESCRIPTION NAME": "Lipid Profile",
        "Agreed price": 6000
      },
      {
        "PRESCRIPTION NAME": "Chest For Ribs (Obliques)",
        "Agreed price": 6000
      },
      {
        "PRESCRIPTION NAME": "Abdominopelvic",
        "Agreed price": 6000
      },
      {
        "PRESCRIPTION NAME": "Thyroid",
        "Agreed price": 6000
      },
      {
        "PRESCRIPTION NAME": "Scrotal",
        "Agreed price": 6000
      },
      {
        "PRESCRIPTION NAME": "Prostate",
        "Agreed price": 6000
      },
      {
        "PRESCRIPTION NAME": "MENOGON 75 IU (per pack)",
        "Agreed price": 6175
      },
      {
        "PRESCRIPTION NAME": "COSOPT EYE DROP",
        "Agreed price": 6250
      },
      {
        "PRESCRIPTION NAME": "Pelvimetry",
        "Agreed price": 6250
      },
      {
        "PRESCRIPTION NAME": "MEROPENEM 1G INJ (PER AMP)",
        "Agreed price": 6500
      },
      {
        "PRESCRIPTION NAME": "Liver Function Test",
        "Agreed price": 6500
      },
      {
        "PRESCRIPTION NAME": "Thigh (Femur)",
        "Agreed price": 6500
      },
      {
        "PRESCRIPTION NAME": "SERETIDE DISKUS- ADULT (per pack)",
        "Agreed price": 7000
      },
      {
        "PRESCRIPTION NAME": "Typhoid Vaccine",
        "Agreed price": 7000
      },
      {
        "PRESCRIPTION NAME": "Shoulder",
        "Agreed price": 7000
      },
      {
        "PRESCRIPTION NAME": "Hip Joint",
        "Agreed price": 7000
      },
      {
        "PRESCRIPTION NAME": "Pelvic (AP)",
        "Agreed price": 7000
      },
      {
        "PRESCRIPTION NAME": "Chest (PA & Lateral)",
        "Agreed price": 7000
      },
      {
        "PRESCRIPTION NAME": "Cervical Spine",
        "Agreed price": 7000
      },
      {
        "PRESCRIPTION NAME": "Abdomen (Erect /Supine)",
        "Agreed price": 7000
      },
      {
        "PRESCRIPTION NAME": "Abdomen (Erect & Supine)",
        "Agreed price": 7000
      },
      {
        "PRESCRIPTION NAME": "Skull (AP & Lat)",
        "Agreed price": 7000
      },
      {
        "PRESCRIPTION NAME": "Mastoids",
        "Agreed price": 7000
      },
      {
        "PRESCRIPTION NAME": "Paranasal Sinuses",
        "Agreed price": 7000
      },
      {
        "PRESCRIPTION NAME": "Mandibles (Jaws)",
        "Agreed price": 7000
      },
      {
        "PRESCRIPTION NAME": "Breast",
        "Agreed price": 7000
      },
      {
        "PRESCRIPTION NAME": "XALATAN EYE DROP (per bot)",
        "Agreed price": 7475
      },
      {
        "PRESCRIPTION NAME": "Specialist consultation follow up",
        "Agreed price": 7500
      },
      {
        "PRESCRIPTION NAME": "Semi-Private Ward Per Diem",
        "Agreed price": 7500
      },
      {
        "PRESCRIPTION NAME": "Gastric Lavage",
        "Agreed price": 7500
      },
      {
        "PRESCRIPTION NAME": "Thoracic Spine",
        "Agreed price": 7500
      },
      {
        "PRESCRIPTION NAME": "Rotavirus Vaccine",
        "Agreed price": 7812.5
      },
      {
        "PRESCRIPTION NAME": "Thoraco Lumbar Spine",
        "Agreed price": 8000
      },
      {
        "PRESCRIPTION NAME": "Lumbo Sacral Spine",
        "Agreed price": 8000
      },
      {
        "PRESCRIPTION NAME": "Chicken Pox Vaccine",
        "Agreed price": 8593.75
      },
      {
        "PRESCRIPTION NAME": "TRAVANTAN EYE DROP (per bot)",
        "Agreed price": 8612.5
      },
      {
        "PRESCRIPTION NAME": "Pelvic & Hip",
        "Agreed price": 9000
      },
      {
        "PRESCRIPTION NAME": "Private Ward Per Diem",
        "Agreed price": 10000
      },
      {
        "PRESCRIPTION NAME": "Incision & Drainage",
        "Agreed price": 10000
      },
      {
        "PRESCRIPTION NAME": "Catheterisation Of Urinary Bladder + Urine Bag",
        "Agreed price": 10000
      },
      {
        "PRESCRIPTION NAME": "Circumcision Of Male Baby",
        "Agreed price": 10000
      },
      {
        "PRESCRIPTION NAME": "Skull (PA/Lat/Townes)",
        "Agreed price": 10000
      },
      {
        "PRESCRIPTION NAME": "Temporo-Mandibular Joints (TMJ)",
        "Agreed price": 10000
      },
      {
        "PRESCRIPTION NAME": "Anaesthesia(Local)",
        "Agreed price": 10000
      },
      {
        "PRESCRIPTION NAME": "ERYTHRPOETIN  2000IU (per amp)",
        "Agreed price": 10562.5
      },
      {
        "PRESCRIPTION NAME": "SUPREFACT INJ (per vial)",
        "Agreed price": 12187.5
      },
      {
        "PRESCRIPTION NAME": "Specialist consultation",
        "Agreed price": 12500
      },
      {
        "PRESCRIPTION NAME": "Theatre use (Minor)",
        "Agreed price": 15000
      },
      {
        "PRESCRIPTION NAME": "Transfussion Of Screened Blood (Rh +Ve)",
        "Agreed price": 20000
      },
      {
        "PRESCRIPTION NAME": "Minor Debridement Of Burns",
        "Agreed price": 20000
      },
      {
        "PRESCRIPTION NAME": "Repair Of Minor Laceration",
        "Agreed price": 20000
      },
      {
        "PRESCRIPTION NAME": "Birth Before Arrival (Bba) Care",
        "Agreed price": 20000
      },
      {
        "PRESCRIPTION NAME": "Transfussion Of Screened Blood (Rh -Ve)",
        "Agreed price": 25000
      },
      {
        "PRESCRIPTION NAME": "Theatre use - Intermediate",
        "Agreed price": 30000
      },
      {
        "PRESCRIPTION NAME": "Ganglion Excision",
        "Agreed price": 30000
      },
      {
        "PRESCRIPTION NAME": "Small Cyst Excision",
        "Agreed price": 30000
      },
      {
        "PRESCRIPTION NAME": "Biopsy Of Tumour Of Abdominal Wall",
        "Agreed price": 30000
      },
      {
        "PRESCRIPTION NAME": "Lumps Excision",
        "Agreed price": 30000
      },
      {
        "PRESCRIPTION NAME": "Electrofulguration Of Condylomata Acuminata",
        "Agreed price": 30000
      },
      {
        "PRESCRIPTION NAME": "Injection Sclerotherapy Of Varicose Veins",
        "Agreed price": 30000
      },
      {
        "PRESCRIPTION NAME": "Excision Of Tophi",
        "Agreed price": 30000
      },
      {
        "PRESCRIPTION NAME": "Pollicisation Of The Index Finger",
        "Agreed price": 30000
      },
      {
        "PRESCRIPTION NAME": "Release Of Chordae",
        "Agreed price": 30000
      },
      {
        "PRESCRIPTION NAME": "Anaesthesia-Intermediate",
        "Agreed price": 35000
      },
      {
        "PRESCRIPTION NAME": "Theatre use - Major",
        "Agreed price": 40000
      },
      {
        "PRESCRIPTION NAME": "Antenatal Care (Including Tests And Scan X2)With Gen. Practitioner",
        "Agreed price": 40000
      },
      {
        "PRESCRIPTION NAME": "Rhogam Injection",
        "Agreed price": 40000
      },
      {
        "PRESCRIPTION NAME": "Anaesthesia-Major",
        "Agreed price": 50000
      },
      {
        "PRESCRIPTION NAME": "Antenatal Care With Obstetrician (Subject To Pre-Authorisation)",
        "Agreed price": 50000
      },
      {
        "PRESCRIPTION NAME": "Normal Delivery (With Or Without Episiotomy)",
        "Agreed price": 60000
      },
      {
        "PRESCRIPTION NAME": "Vulvectomy",
        "Agreed price": 75000
      },
      {
        "PRESCRIPTION NAME": "Ventrosuspension Of The Bladder",
        "Agreed price": 75000
      },
      {
        "PRESCRIPTION NAME": "Tubal Reconstruction",
        "Agreed price": 75000
      },
      {
        "PRESCRIPTION NAME": "Multiple Delivery",
        "Agreed price": 80000
      },
      {
        "PRESCRIPTION NAME": "Vaginoclesis",
        "Agreed price": 80000
      },
      {
        "PRESCRIPTION NAME": "Assisted Delivery (Vacuum, Instrumental)",
        "Agreed price": 90000
      },
      {
        "PRESCRIPTION NAME": "Wedge Resection Of The Ovary",
        "Agreed price": 100000
      },
      {
        "PRESCRIPTION NAME": "Amputation Of Cervix",
        "Agreed price": 100000
      },
      {
        "PRESCRIPTION NAME": "Ovariectomy",
        "Agreed price": 100000
      },
      {
        "PRESCRIPTION NAME": "Salpingo-Oophoreictomy",
        "Agreed price": 100000
      },
      {
        "PRESCRIPTION NAME": "Ovarian Biopsy",
        "Agreed price": 100000
      },
      {
        "PRESCRIPTION NAME": "Pelvic/Abdominal Abscess Drainage",
        "Agreed price": 120000
      },
      {
        "PRESCRIPTION NAME": "Pelvic Haematocoele",
        "Agreed price": 120000
      },
      {
        "PRESCRIPTION NAME": "Reconstruction Of Vagina",
        "Agreed price": 150000
      },
      {
        "PRESCRIPTION NAME": "Ectopic Pregnancy",
        "Agreed price": 150000
      },
      {
        "PRESCRIPTION NAME": "Laparotomy Diagnostic/Therapeutic, Inter-Sex",
        "Agreed price": 150000
      },
      {
        "PRESCRIPTION NAME": "Ovarian Cysts",
        "Agreed price": 150000
      },
      {
        "PRESCRIPTION NAME": "Broad Ligament Haematoma",
        "Agreed price": 150000
      },
      {
        "PRESCRIPTION NAME": "Colporrhaphy/Colpoperineorrhaphy",
        "Agreed price": 150000
      },
      {
        "PRESCRIPTION NAME": "Vaginal Hysterectomy/Manchester Repair",
        "Agreed price": 150000
      },
      {
        "PRESCRIPTION NAME": "Ventrosuspension Procedures Of Correction Of Uterine",
        "Agreed price": 150000
      },
      {
        "PRESCRIPTION NAME": "Repair Of Inverted Uterus",
        "Agreed price": 150000
      },
      {
        "PRESCRIPTION NAME": "Repair Of Perforated/Ruptured Uterus",
        "Agreed price": 150000
      },
      {
        "PRESCRIPTION NAME": "Rectovaginal Fistula Repair",
        "Agreed price": 150000
      },
      {
        "PRESCRIPTION NAME": "Hysterectomy",
        "Agreed price": 180000
      },
      {
        "PRESCRIPTION NAME": "Hysterectomy And Bilateral Salpingo-Oophorectomy",
        "Agreed price": 180000
      },
      {
        "PRESCRIPTION NAME": "Reconstruction Surgery E.g Straussman Operation",
        "Agreed price": 180000
      },
      {
        "PRESCRIPTION NAME": "Vesicovaginal Fistula Repair",
        "Agreed price": 180000
      },
      {
        "PRESCRIPTION NAME": "Ceasarean Section (All inclussive)",
        "Agreed price": 350000
      },
      {
        "PRESCRIPTION NAME": "Myomectomy (All inclussive)",
        "Agreed price": 500000
      }
    ]
  }